{"assets":{"21580B63D286D4108E5375F46570ABFA":{"type":"texture","index":10,"assetRequest":{"type":"slide","state":"contents","slide":"none"},"url":{"native":"assets\/7357638D-A141-4D3C-853E-8AEAB96EAAA9.pdf"},"width":1920,"height":1080},"0FC7CF7E41C9F9791A396D66F4460126":{"type":"texture","index":9,"assetRequest":{"type":"slide","state":"contents","slide":"none"},"url":{"native":"assets\/7357638D-A141-4D3C-853E-8AEAB96EAAA9.pdf"},"width":1920,"height":1080},"08CFE66A480ED77D2CFE6207C3B1E0F5":{"type":"texture","index":5,"assetRequest":{"type":"slide","state":"contents","slide":"none"},"url":{"native":"assets\/7357638D-A141-4D3C-853E-8AEAB96EAAA9.pdf"},"width":1319,"height":43},"B27A68FB23B3E8F4E1257CCC1DAB565D":{"type":"texture","index":2,"assetRequest":{"type":"slide","state":"contents","slide":"none"},"url":{"native":"assets\/7357638D-A141-4D3C-853E-8AEAB96EAAA9.pdf"},"width":1274,"height":45},"C1D05F54FBF927BDB7F1A842AC0F0C26":{"type":"texture","index":8,"assetRequest":{"type":"slide","state":"contents","slide":"none"},"url":{"native":"assets\/7357638D-A141-4D3C-853E-8AEAB96EAAA9.pdf"},"width":273,"height":23},"F119794F38BEBA339B2ADE97DA30ED22":{"type":"texture","index":4,"assetRequest":{"type":"slide","state":"contents","slide":"none"},"url":{"native":"assets\/7357638D-A141-4D3C-853E-8AEAB96EAAA9.pdf"},"width":448,"height":35},"C25C25FF361FB24FC35F6B120D2F252D":{"type":"texture","index":0,"assetRequest":{"type":"slide","state":"contents","slide":"none"},"url":{"native":"assets\/7357638D-A141-4D3C-853E-8AEAB96EAAA9.pdf"},"width":1920,"height":1080},"F70806264CCD7A2CE6EF76B234FDC22B":{"type":"texture","index":1,"assetRequest":{"type":"slide","state":"contents","slide":"none"},"url":{"native":"assets\/7357638D-A141-4D3C-853E-8AEAB96EAAA9.pdf"},"width":289,"height":65},"5DE7B0CC278EBD77E051848EF72AD393":{"type":"texture","index":6,"assetRequest":{"type":"slide","state":"contents","slide":"none"},"url":{"native":"assets\/7357638D-A141-4D3C-853E-8AEAB96EAAA9.pdf"},"width":1454,"height":43},"C51349F0E43DB4FB3CF1ABCE18B00245":{"type":"texture","index":3,"assetRequest":{"type":"slide","state":"contents","slide":"none"},"url":{"native":"assets\/7357638D-A141-4D3C-853E-8AEAB96EAAA9.pdf"},"width":1095,"height":42},"08B4C58F6D9A95559DC4A3C6C6CDFBCB":{"type":"texture","index":7,"assetRequest":{"type":"slide","state":"contents","slide":"none"},"url":{"native":"assets\/7357638D-A141-4D3C-853E-8AEAB96EAAA9.pdf"},"width":1299,"height":296}},"events":[{"effects":[{"beginTime":0,"baseLayer":{"animations":[],"initialState":{"affineTransform":[1,0,0,1,0,0],"masksToBounds":false,"rotation":0,"scale":1,"position":{"pointX":719.9969291687014,"pointY":466.20831298828102},"width":1319.0000000000002,"sublayerTransform":[1,0,0,0,0,1,0,0,0,0,1,0,0,0,0,1],"contentsRect":{"y":0,"x":0,"width":1,"height":1},"opacity":1,"edgeAntialiasingMask":251658240,"height":306,"hidden":false,"anchorPoint":{"pointX":0.5,"pointY":0.5}},"objectID":"980187A1-807D-44E5-BF98-5A56903D5780","layers":[{"animations":[],"initialState":{"affineTransform":[1,0,0,1,0,0],"masksToBounds":false,"rotation":0,"scale":1,"position":{"pointX":899.50307083129871,"pointY":226.79168701171898},"width":1319.0000000000002,"sublayerTransform":[1,0,0,0,0,1,0,0,0,0,1,-0.00035007912466775983,0,0,0,1],"contentsRect":{"y":0,"x":0,"width":1,"height":1},"opacity":1,"edgeAntialiasingMask":251658240,"height":306,"hidden":false,"anchorPoint":{"pointX":0.68195835544450234,"pointY":0.74114930395986589}},"layers":[{"animations":[{"additive":false,"timeOffset":0,"beginTime":1e-100,"repeatCount":0,"fillMode":"both","duration":0.01,"autoreverses":false,"animations":[{"additive":false,"timeOffset":0,"beginTime":0,"from":{"scalar":true},"repeatCount":0,"fillMode":"both","duration":0.0001,"autoreverses":false,"property":"hidden","to":{"scalar":false},"removedOnCompletion":true},{"additive":false,"timeOffset":0,"beginTime":0.0001,"from":{"scalar":false},"repeatCount":0,"fillMode":"forwards","duration":0.0099000000000000008,"autoreverses":false,"property":"hidden","to":{"scalar":false},"removedOnCompletion":true}],"removedOnCompletion":false}],"layers":[],"texturedRectangle":{"singleTextureOpacity":1,"textXHeight":0.46961805555555558,"textBaseline":0.74317084418402779,"isBackgroundTexture":false,"isVerticalText":false,"textColor":[0.21997910737991333,0.21857796609401703,0.22138024866580963,1],"textureType":6},"initialState":{"affineTransform":[1,0,0,1,0,0],"masksToBounds":false,"rotation":0,"scale":1,"position":{"pointX":643.50307083129871,"pointY":30.291687011718977},"width":1274,"sublayerTransform":[1,0,0,0,0,1,0,0,0,0,1,0,0,0,0,1],"contentsRect":{"y":0,"x":0,"width":1,"height":1},"opacity":1,"edgeAntialiasingMask":0,"height":45,"hidden":true,"anchorPoint":{"pointX":0.5,"pointY":0.5}},"texture":"B27A68FB23B3E8F4E1257CCC1DAB565D"}]},{"animations":[],"layers":[],"texturedRectangle":{"singleTextureOpacity":1,"textXHeight":0.50316220238095233,"textBaseline":0.75577825875509352,"isBackgroundTexture":false,"isVerticalText":false,"textColor":[0.21997910737991333,0.21857796609401703,0.22138024866580963,1],"textureType":6},"initialState":{"affineTransform":[1,0,0,1,0,0],"masksToBounds":false,"rotation":0,"scale":1,"position":{"pointX":554.00307083129871,"pointY":117.79168701171898},"width":1095,"sublayerTransform":[1,0,0,0,0,1,0,0,0,0,1,0,0,0,0,1],"contentsRect":{"y":0,"x":0,"width":1,"height":1},"opacity":1,"edgeAntialiasingMask":0,"height":42,"hidden":true,"anchorPoint":{"pointX":0.5,"pointY":0.5}},"texture":"C51349F0E43DB4FB3CF1ABCE18B00245"},{"animations":[],"layers":[],"texturedRectangle":{"singleTextureOpacity":1,"textXHeight":0.6037946428571429,"textBaseline":0.9155053070613316,"isBackgroundTexture":false,"isVerticalText":false,"textColor":[0.21997910737991333,0.21857796609401703,0.22138024866580963,1],"textureType":6},"initialState":{"affineTransform":[1,0,0,1,0,0],"masksToBounds":false,"rotation":0,"scale":1,"position":{"pointX":230.50307083129869,"pointY":201.29168701171898},"width":448,"sublayerTransform":[1,0,0,0,0,1,0,0,0,0,1,0,0,0,0,1],"contentsRect":{"y":0,"x":0,"width":1,"height":1},"opacity":1,"edgeAntialiasingMask":0,"height":35,"hidden":true,"anchorPoint":{"pointX":0.5,"pointY":0.5}},"texture":"F119794F38BEBA339B2ADE97DA30ED22"},{"animations":[],"layers":[],"texturedRectangle":{"singleTextureOpacity":1,"textXHeight":0.49146075581395349,"textBaseline":0.75215545643207637,"isBackgroundTexture":false,"isVerticalText":false,"textColor":[0.21997910737991333,0.21857796609401703,0.22138024866580963,1],"textureType":6},"initialState":{"affineTransform":[1,0,0,1,0,0],"masksToBounds":false,"rotation":0,"scale":1,"position":{"pointX":666.00307083129871,"pointY":292.29168701171898},"width":1319,"sublayerTransform":[1,0,0,0,0,1,0,0,0,0,1,0,0,0,0,1],"contentsRect":{"y":0,"x":0,"width":1,"height":1},"opacity":1,"edgeAntialiasingMask":0,"height":43,"hidden":true,"anchorPoint":{"pointX":0.5,"pointY":0.5}},"texture":"08CFE66A480ED77D2CFE6207C3B1E0F5"}]},"effects":[],"duration":0.01,"type":"buildIn","attributes":{"direction":0},"name":"apple:bc-appear","objectID":"980187A1-807D-44E5-BF98-5A56903D5780"}],"automaticPlay":false,"hyperlinks":[],"accessibility":[{"text":"Results","targetRectangle":{"y":89,"x":99,"width":291.80500026598571,"height":100.53440856933594}},{"text":"Alison M. Ashbury, 2022-05-30","targetRectangle":{"y":1050.6215823888779,"x":1643.8827819824219,"width":269.873046875,"height":24}},{"text":"What does my audience need to know in order to trust the conclusions of my study?","targetRectangle":{"y":222.68760621547699,"x":103.45411682128906,"width":1452.8125,"height":47}}],"baseLayer":{"animations":[],"initialState":{"affineTransform":[1,0,0,1,0,0],"masksToBounds":false,"rotation":0,"scale":1,"position":{"pointX":960,"pointY":540},"width":1920,"sublayerTransform":[1,0,0,0,0,1,0,0,0,0,1,0,0,0,0,1],"contentsRect":{"y":0,"x":0,"width":1,"height":1},"opacity":1,"edgeAntialiasingMask":251658240,"height":1080,"hidden":false,"anchorPoint":{"pointX":0.5,"pointY":0.5}},"layers":[{"animations":[],"initialState":{"affineTransform":[1,0,0,1,0,0],"masksToBounds":false,"rotation":0,"scale":1,"position":{"pointX":960,"pointY":540},"width":1920,"sublayerTransform":[1,0,0,0,0,1,0,0,0,0,1,0,0,0,0,1],"contentsRect":{"y":0,"x":0,"width":1,"height":1},"opacity":1,"edgeAntialiasingMask":251658240,"height":1080,"hidden":false,"anchorPoint":{"pointX":0.5,"pointY":0.5}},"layers":[{"animations":[],"initialState":{"affineTransform":[1,0,0,1,0,0],"masksToBounds":false,"rotation":0,"scale":1,"position":{"pointX":960,"pointY":540},"width":1920,"sublayerTransform":[1,0,0,0,0,1,0,0,0,0,1,0,0,0,0,1],"contentsRect":{"y":0,"x":0,"width":1,"height":1},"opacity":1,"edgeAntialiasingMask":251658240,"height":1080,"hidden":false,"anchorPoint":{"pointX":0.5,"pointY":0.5}},"layers":[{"animations":[],"layers":[],"texturedRectangle":{"isBackgroundTexture":true,"singleTextureOpacity":1,"textureType":1,"textBaseline":0,"textXHeight":0,"isVerticalText":false},"initialState":{"affineTransform":[1,0,0,1,0,0],"masksToBounds":false,"rotation":0,"scale":1,"position":{"pointX":960,"pointY":540},"width":1920,"sublayerTransform":[1,0,0,0,0,1,0,0,0,0,1,0,0,0,0,1],"contentsRect":{"y":0,"x":0,"width":1,"height":1},"opacity":1,"edgeAntialiasingMask":0,"height":1080,"hidden":false,"anchorPoint":{"pointX":0.5,"pointY":0.5}},"texture":"C25C25FF361FB24FC35F6B120D2F252D"}]}]},{"animations":[],"initialState":{"affineTransform":[1,0,0,1,0,0],"masksToBounds":false,"rotation":0,"scale":1,"position":{"pointX":960,"pointY":540},"width":1920,"sublayerTransform":[1,0,0,0,0,1,0,0,0,0,1,0,0,0,0,1],"contentsRect":{"y":0,"x":0,"width":1,"height":1},"opacity":1,"edgeAntialiasingMask":251658240,"height":1080,"hidden":false,"anchorPoint":{"pointX":0.5,"pointY":0.5}},"layers":[{"animations":[],"initialState":{"affineTransform":[1,0,0,1,0,0],"masksToBounds":false,"rotation":0,"scale":1,"position":{"pointX":239.50000000000006,"pointY":117.50000000000003},"width":289,"sublayerTransform":[1,0,0,0,0,1,0,0,0,0,1,0,0,0,0,1],"contentsRect":{"y":0,"x":0,"width":1,"height":1},"opacity":1,"edgeAntialiasingMask":251658240,"height":65,"hidden":false,"anchorPoint":{"pointX":0.5,"pointY":0.5}},"layers":[{"animations":[],"layers":[],"texturedRectangle":{"singleTextureOpacity":1,"textXHeight":0.67607692307692313,"textBaseline":0.9552278958834135,"isBackgroundTexture":true,"isVerticalText":false,"textColor":[0,0,0,1],"textureType":6},"initialState":{"affineTransform":[1,0,0,1,0,0],"masksToBounds":false,"rotation":0,"scale":1,"position":{"pointX":152.49999999999994,"pointY":56.499999999999972},"width":289,"sublayerTransform":[1,0,0,0,0,1,0,0,0,0,1,0,0,0,0,1],"contentsRect":{"y":0,"x":0,"width":1,"height":1},"opacity":1,"edgeAntialiasingMask":0,"height":65,"hidden":false,"anchorPoint":{"pointX":0.5,"pointY":0.5}},"texture":"F70806264CCD7A2CE6EF76B234FDC22B"}]}]},{"animations":[],"initialState":{"affineTransform":[1,0,0,1,0,0],"masksToBounds":false,"rotation":0,"scale":1,"position":{"pointX":960,"pointY":540},"width":1920,"sublayerTransform":[1,0,0,0,0,1,0,0,0,0,1,0,0,0,0,1],"contentsRect":{"y":0,"x":0,"width":1,"height":1},"opacity":1,"edgeAntialiasingMask":251658240,"height":1080,"hidden":false,"anchorPoint":{"pointX":0.5,"pointY":0.5}},"layers":[{"animations":[],"initialState":{"affineTransform":[1,0,0,1,0,0],"masksToBounds":false,"rotation":0,"scale":1,"position":{"pointX":719.9969291687014,"pointY":466.20831298828102},"width":1319.0000000000002,"sublayerTransform":[1,0,0,0,0,1,0,0,0,0,1,0,0,0,0,1],"contentsRect":{"y":0,"x":0,"width":1,"height":1},"opacity":1,"edgeAntialiasingMask":251658240,"height":306,"hidden":false,"anchorPoint":{"pointX":0.5,"pointY":0.5}},"objectID":"980187A1-807D-44E5-BF98-5A56903D5780","layers":[{"animations":[],"layers":[],"texturedRectangle":{"singleTextureOpacity":1,"textXHeight":0.46961805555555558,"textBaseline":0.74317084418402779,"isBackgroundTexture":false,"isVerticalText":false,"textColor":[0.21997910737991333,0.21857796609401703,0.22138024866580963,1],"textureType":6},"initialState":{"affineTransform":[1,0,0,1,0,0],"masksToBounds":false,"rotation":0,"scale":1,"position":{"pointX":643.50307083129871,"pointY":30.291687011718977},"width":1274,"sublayerTransform":[1,0,0,0,0,1,0,0,0,0,1,0,0,0,0,1],"contentsRect":{"y":0,"x":0,"width":1,"height":1},"opacity":1,"edgeAntialiasingMask":0,"height":45,"hidden":true,"anchorPoint":{"pointX":0.5,"pointY":0.5}},"texture":"B27A68FB23B3E8F4E1257CCC1DAB565D"},{"animations":[],"layers":[],"texturedRectangle":{"singleTextureOpacity":1,"textXHeight":0.50316220238095233,"textBaseline":0.75577825875509352,"isBackgroundTexture":false,"isVerticalText":false,"textColor":[0.21997910737991333,0.21857796609401703,0.22138024866580963,1],"textureType":6},"initialState":{"affineTransform":[1,0,0,1,0,0],"masksToBounds":false,"rotation":0,"scale":1,"position":{"pointX":554.00307083129871,"pointY":117.79168701171898},"width":1095,"sublayerTransform":[1,0,0,0,0,1,0,0,0,0,1,0,0,0,0,1],"contentsRect":{"y":0,"x":0,"width":1,"height":1},"opacity":1,"edgeAntialiasingMask":0,"height":42,"hidden":true,"anchorPoint":{"pointX":0.5,"pointY":0.5}},"texture":"C51349F0E43DB4FB3CF1ABCE18B00245"},{"animations":[],"layers":[],"texturedRectangle":{"singleTextureOpacity":1,"textXHeight":0.6037946428571429,"textBaseline":0.9155053070613316,"isBackgroundTexture":false,"isVerticalText":false,"textColor":[0.21997910737991333,0.21857796609401703,0.22138024866580963,1],"textureType":6},"initialState":{"affineTransform":[1,0,0,1,0,0],"masksToBounds":false,"rotation":0,"scale":1,"position":{"pointX":230.50307083129869,"pointY":201.29168701171898},"width":448,"sublayerTransform":[1,0,0,0,0,1,0,0,0,0,1,0,0,0,0,1],"contentsRect":{"y":0,"x":0,"width":1,"height":1},"opacity":1,"edgeAntialiasingMask":0,"height":35,"hidden":true,"anchorPoint":{"pointX":0.5,"pointY":0.5}},"texture":"F119794F38BEBA339B2ADE97DA30ED22"},{"animations":[],"layers":[],"texturedRectangle":{"singleTextureOpacity":1,"textXHeight":0.49146075581395349,"textBaseline":0.75215545643207637,"isBackgroundTexture":false,"isVerticalText":false,"textColor":[0.21997910737991333,0.21857796609401703,0.22138024866580963,1],"textureType":6},"initialState":{"affineTransform":[1,0,0,1,0,0],"masksToBounds":false,"rotation":0,"scale":1,"position":{"pointX":666.00307083129871,"pointY":292.29168701171898},"width":1319,"sublayerTransform":[1,0,0,0,0,1,0,0,0,0,1,0,0,0,0,1],"contentsRect":{"y":0,"x":0,"width":1,"height":1},"opacity":1,"edgeAntialiasingMask":0,"height":43,"hidden":true,"anchorPoint":{"pointX":0.5,"pointY":0.5}},"texture":"08CFE66A480ED77D2CFE6207C3B1E0F5"}]}]},{"animations":[],"initialState":{"affineTransform":[1,0,0,1,0,0],"masksToBounds":false,"rotation":0,"scale":1,"position":{"pointX":960,"pointY":540},"width":1920,"sublayerTransform":[1,0,0,0,0,1,0,0,0,0,1,0,0,0,0,1],"contentsRect":{"y":0,"x":0,"width":1,"height":1},"opacity":1,"edgeAntialiasingMask":251658240,"height":1080,"hidden":false,"anchorPoint":{"pointX":0.5,"pointY":0.5}},"layers":[{"animations":[],"initialState":{"affineTransform":[1,0,0,1,0,0],"masksToBounds":false,"rotation":0,"scale":1,"position":{"pointX":826.45411682128906,"pointY":240.18760621547699},"width":1454,"sublayerTransform":[1,0,0,0,0,1,0,0,0,0,1,0,0,0,0,1],"contentsRect":{"y":0,"x":0,"width":1,"height":1},"opacity":1,"edgeAntialiasingMask":251658240,"height":43,"hidden":false,"anchorPoint":{"pointX":0.5,"pointY":0.5}},"layers":[{"animations":[],"layers":[],"texturedRectangle":{"singleTextureOpacity":1,"textXHeight":0.49146075581395349,"textBaseline":0.76562747012737187,"isBackgroundTexture":true,"isVerticalText":false,"textColor":[0.21997910737991333,0.21857796609401703,0.22138024866580963,1],"textureType":6},"initialState":{"affineTransform":[1,0,0,1,0,0],"masksToBounds":false,"rotation":0,"scale":1,"position":{"pointX":732.54588317871094,"pointY":29.81239378452301},"width":1454,"sublayerTransform":[1,0,0,0,0,1,0,0,0,0,1,0,0,0,0,1],"contentsRect":{"y":0,"x":0,"width":1,"height":1},"opacity":1,"edgeAntialiasingMask":0,"height":43,"hidden":false,"anchorPoint":{"pointX":0.5,"pointY":0.5}},"texture":"5DE7B0CC278EBD77E051848EF72AD393"}]}]},{"animations":[],"initialState":{"affineTransform":[1,0,0,1,0,0],"masksToBounds":false,"rotation":0,"scale":1,"position":{"pointX":960,"pointY":540},"width":1920,"sublayerTransform":[1,0,0,0,0,1,0,0,0,0,1,0,0,0,0,1],"contentsRect":{"y":0,"x":0,"width":1,"height":1},"opacity":1,"edgeAntialiasingMask":251658240,"height":1080,"hidden":false,"anchorPoint":{"pointX":0.5,"pointY":0.5}},"layers":[{"animations":[],"initialState":{"affineTransform":[1,0,0,1,0,0],"masksToBounds":false,"rotation":0,"scale":1,"position":{"pointX":742.04576110839832,"pointY":793.44873046874977},"width":1299,"sublayerTransform":[1,0,0,0,0,1,0,0,0,0,1,0,0,0,0,1],"contentsRect":{"y":0,"x":0,"width":1,"height":1},"opacity":1,"edgeAntialiasingMask":251658240,"height":296,"hidden":false,"anchorPoint":{"pointX":0.5,"pointY":0.5}},"objectID":"0CF4FF1B-C915-4A9D-816F-AAEFF1151945","layers":[{"animations":[],"layers":[],"texturedRectangle":{"singleTextureOpacity":1,"textXHeight":0.048191379856418921,"textBaseline":-0.14375428895692569,"isBackgroundTexture":true,"isVerticalText":false,"textColor":[0.37036359310150146,0.37036353349685669,0.37036359310150146,1],"textureType":6},"initialState":{"affineTransform":[1,0,0,1,0,0],"masksToBounds":false,"rotation":0,"scale":1,"position":{"pointX":650.95423889160168,"pointY":190.55126953125023},"width":1299,"sublayerTransform":[1,0,0,0,0,1,0,0,0,0,1,0,0,0,0,1],"contentsRect":{"y":0,"x":0,"width":1,"height":1},"opacity":1,"edgeAntialiasingMask":0,"height":296,"hidden":true,"anchorPoint":{"pointX":0.5,"pointY":0.5}},"texture":"08B4C58F6D9A95559DC4A3C6C6CDFBCB"}]}]},{"animations":[],"initialState":{"affineTransform":[1,0,0,1,0,0],"masksToBounds":false,"rotation":0,"scale":1,"position":{"pointX":960,"pointY":540},"width":1920,"sublayerTransform":[1,0,0,0,0,1,0,0,0,0,1,0,0,0,0,1],"contentsRect":{"y":0,"x":0,"width":1,"height":1},"opacity":1,"edgeAntialiasingMask":251658240,"height":1080,"hidden":false,"anchorPoint":{"pointX":0.5,"pointY":0.5}},"layers":[{"animations":[],"initialState":{"affineTransform":[1,0,0,1,0,0],"masksToBounds":false,"rotation":0,"scale":1,"position":{"pointX":1748.673583984375,"pointY":1058.1215823888779},"width":273,"sublayerTransform":[1,0,0,0,0,1,0,0,0,0,1,0,0,0,0,1],"contentsRect":{"y":0,"x":0,"width":1,"height":1},"opacity":1,"edgeAntialiasingMask":251658240,"height":23,"hidden":false,"anchorPoint":{"pointX":0.5,"pointY":0.5}},"layers":[{"animations":[],"layers":[],"texturedRectangle":{"singleTextureOpacity":1,"textXHeight":0.45940896739130432,"textBaseline":0.72777260386425513,"isBackgroundTexture":true,"isVerticalText":false,"textColor":[0.83603078126907349,0.83603072166442871,0.83603072166442871,1],"textureType":6},"initialState":{"affineTransform":[1,0,0,1,0,0],"masksToBounds":false,"rotation":0,"scale":1,"position":{"pointX":166.326416015625,"pointY":17.878417611122131},"width":273,"sublayerTransform":[1,0,0,0,0,1,0,0,0,0,1,0,0,0,0,1],"contentsRect":{"y":0,"x":0,"width":1,"height":1},"opacity":1,"edgeAntialiasingMask":0,"height":23,"hidden":false,"anchorPoint":{"pointX":0.5,"pointY":0.5}},"texture":"C1D05F54FBF927BDB7F1A842AC0F0C26"}]}]}]}},{"effects":[{"beginTime":0,"baseLayer":{"animations":[],"initialState":{"affineTransform":[1,0,0,1,0,0],"masksToBounds":false,"rotation":0,"scale":1,"position":{"pointX":719.9969291687014,"pointY":466.20831298828102},"width":1319.0000000000002,"sublayerTransform":[1,0,0,0,0,1,0,0,0,0,1,0,0,0,0,1],"contentsRect":{"y":0,"x":0,"width":1,"height":1},"opacity":1,"edgeAntialiasingMask":251658240,"height":306,"hidden":false,"anchorPoint":{"pointX":0.5,"pointY":0.5}},"objectID":"980187A1-807D-44E5-BF98-5A56903D5780","layers":[{"animations":[],"layers":[],"texturedRectangle":{"singleTextureOpacity":1,"textXHeight":0.46961805555555558,"textBaseline":0.74317084418402779,"isBackgroundTexture":false,"isVerticalText":false,"textColor":[0.21997910737991333,0.21857796609401703,0.22138024866580963,1],"textureType":6},"initialState":{"affineTransform":[1,0,0,1,0,0],"masksToBounds":false,"rotation":0,"scale":1,"position":{"pointX":643.50307083129871,"pointY":30.291687011718977},"width":1274,"sublayerTransform":[1,0,0,0,0,1,0,0,0,0,1,0,0,0,0,1],"contentsRect":{"y":0,"x":0,"width":1,"height":1},"opacity":1,"edgeAntialiasingMask":0,"height":45,"hidden":false,"anchorPoint":{"pointX":0.5,"pointY":0.5}},"texture":"B27A68FB23B3E8F4E1257CCC1DAB565D"},{"animations":[],"initialState":{"affineTransform":[1,0,0,1,0,0],"masksToBounds":false,"rotation":0,"scale":1,"position":{"pointX":899.50307083129871,"pointY":226.79168701171898},"width":1319.0000000000002,"sublayerTransform":[1,0,0,0,0,1,0,0,0,0,1,-0.00035007912466775983,0,0,0,1],"contentsRect":{"y":0,"x":0,"width":1,"height":1},"opacity":1,"edgeAntialiasingMask":251658240,"height":306,"hidden":false,"anchorPoint":{"pointX":0.68195835544450234,"pointY":0.74114930395986589}},"layers":[{"animations":[{"additive":false,"timeOffset":0,"beginTime":1e-100,"repeatCount":0,"fillMode":"both","duration":0.01,"autoreverses":false,"animations":[{"additive":false,"timeOffset":0,"beginTime":0,"from":{"scalar":true},"repeatCount":0,"fillMode":"both","duration":0.0001,"autoreverses":false,"property":"hidden","to":{"scalar":false},"removedOnCompletion":true},{"additive":false,"timeOffset":0,"beginTime":0.0001,"from":{"scalar":false},"repeatCount":0,"fillMode":"forwards","duration":0.0099000000000000008,"autoreverses":false,"property":"hidden","to":{"scalar":false},"removedOnCompletion":true}],"removedOnCompletion":false}],"layers":[],"texturedRectangle":{"singleTextureOpacity":1,"textXHeight":0.50316220238095233,"textBaseline":0.75577825875509352,"isBackgroundTexture":false,"isVerticalText":false,"textColor":[0.21997910737991333,0.21857796609401703,0.22138024866580963,1],"textureType":6},"initialState":{"affineTransform":[1,0,0,1,0,0],"masksToBounds":false,"rotation":0,"scale":1,"position":{"pointX":554.00307083129871,"pointY":117.79168701171898},"width":1095,"sublayerTransform":[1,0,0,0,0,1,0,0,0,0,1,0,0,0,0,1],"contentsRect":{"y":0,"x":0,"width":1,"height":1},"opacity":1,"edgeAntialiasingMask":0,"height":42,"hidden":true,"anchorPoint":{"pointX":0.5,"pointY":0.5}},"texture":"C51349F0E43DB4FB3CF1ABCE18B00245"}]},{"animations":[],"layers":[],"texturedRectangle":{"singleTextureOpacity":1,"textXHeight":0.6037946428571429,"textBaseline":0.9155053070613316,"isBackgroundTexture":false,"isVerticalText":false,"textColor":[0.21997910737991333,0.21857796609401703,0.22138024866580963,1],"textureType":6},"initialState":{"affineTransform":[1,0,0,1,0,0],"masksToBounds":false,"rotation":0,"scale":1,"position":{"pointX":230.50307083129869,"pointY":201.29168701171898},"width":448,"sublayerTransform":[1,0,0,0,0,1,0,0,0,0,1,0,0,0,0,1],"contentsRect":{"y":0,"x":0,"width":1,"height":1},"opacity":1,"edgeAntialiasingMask":0,"height":35,"hidden":true,"anchorPoint":{"pointX":0.5,"pointY":0.5}},"texture":"F119794F38BEBA339B2ADE97DA30ED22"},{"animations":[],"layers":[],"texturedRectangle":{"singleTextureOpacity":1,"textXHeight":0.49146075581395349,"textBaseline":0.75215545643207637,"isBackgroundTexture":false,"isVerticalText":false,"textColor":[0.21997910737991333,0.21857796609401703,0.22138024866580963,1],"textureType":6},"initialState":{"affineTransform":[1,0,0,1,0,0],"masksToBounds":false,"rotation":0,"scale":1,"position":{"pointX":666.00307083129871,"pointY":292.29168701171898},"width":1319,"sublayerTransform":[1,0,0,0,0,1,0,0,0,0,1,0,0,0,0,1],"contentsRect":{"y":0,"x":0,"width":1,"height":1},"opacity":1,"edgeAntialiasingMask":0,"height":43,"hidden":true,"anchorPoint":{"pointX":0.5,"pointY":0.5}},"texture":"08CFE66A480ED77D2CFE6207C3B1E0F5"}]},"effects":[],"duration":0.01,"type":"buildIn","attributes":{"direction":0},"name":"apple:bc-appear","objectID":"980187A1-807D-44E5-BF98-5A56903D5780"}],"automaticPlay":false,"hyperlinks":[],"accessibility":[{"text":"Results","targetRectangle":{"y":89,"x":99,"width":291.80500026598571,"height":100.53440856933594}},{"text":"Alison M. Ashbury, 2022-05-30","targetRectangle":{"y":1050.6215823888779,"x":1643.8827819824219,"width":269.873046875,"height":24}},{"text":"Plainly describe what your data shows (no methods or interpretation)","targetRectangle":{"y":317.20831298828125,"x":110.21121215820312,"width":1231.46484375,"height":47}},{"text":"What does my audience need to know in order to trust the conclusions of my study?","targetRectangle":{"y":222.68760621547699,"x":103.45411682128906,"width":1452.8125,"height":47}}],"baseLayer":{"animations":[],"initialState":{"affineTransform":[1,0,0,1,0,0],"masksToBounds":false,"rotation":0,"scale":1,"position":{"pointX":960,"pointY":540},"width":1920,"sublayerTransform":[1,0,0,0,0,1,0,0,0,0,1,0,0,0,0,1],"contentsRect":{"y":0,"x":0,"width":1,"height":1},"opacity":1,"edgeAntialiasingMask":251658240,"height":1080,"hidden":false,"anchorPoint":{"pointX":0.5,"pointY":0.5}},"layers":[{"animations":[],"initialState":{"affineTransform":[1,0,0,1,0,0],"masksToBounds":false,"rotation":0,"scale":1,"position":{"pointX":960,"pointY":540},"width":1920,"sublayerTransform":[1,0,0,0,0,1,0,0,0,0,1,0,0,0,0,1],"contentsRect":{"y":0,"x":0,"width":1,"height":1},"opacity":1,"edgeAntialiasingMask":251658240,"height":1080,"hidden":false,"anchorPoint":{"pointX":0.5,"pointY":0.5}},"layers":[{"animations":[],"initialState":{"affineTransform":[1,0,0,1,0,0],"masksToBounds":false,"rotation":0,"scale":1,"position":{"pointX":960,"pointY":540},"width":1920,"sublayerTransform":[1,0,0,0,0,1,0,0,0,0,1,0,0,0,0,1],"contentsRect":{"y":0,"x":0,"width":1,"height":1},"opacity":1,"edgeAntialiasingMask":251658240,"height":1080,"hidden":false,"anchorPoint":{"pointX":0.5,"pointY":0.5}},"layers":[{"animations":[],"layers":[],"texturedRectangle":{"isBackgroundTexture":true,"singleTextureOpacity":1,"textureType":1,"textBaseline":0,"textXHeight":0,"isVerticalText":false},"initialState":{"affineTransform":[1,0,0,1,0,0],"masksToBounds":false,"rotation":0,"scale":1,"position":{"pointX":960,"pointY":540},"width":1920,"sublayerTransform":[1,0,0,0,0,1,0,0,0,0,1,0,0,0,0,1],"contentsRect":{"y":0,"x":0,"width":1,"height":1},"opacity":1,"edgeAntialiasingMask":0,"height":1080,"hidden":false,"anchorPoint":{"pointX":0.5,"pointY":0.5}},"texture":"C25C25FF361FB24FC35F6B120D2F252D"}]}]},{"animations":[],"initialState":{"affineTransform":[1,0,0,1,0,0],"masksToBounds":false,"rotation":0,"scale":1,"position":{"pointX":960,"pointY":540},"width":1920,"sublayerTransform":[1,0,0,0,0,1,0,0,0,0,1,0,0,0,0,1],"contentsRect":{"y":0,"x":0,"width":1,"height":1},"opacity":1,"edgeAntialiasingMask":251658240,"height":1080,"hidden":false,"anchorPoint":{"pointX":0.5,"pointY":0.5}},"layers":[{"animations":[],"initialState":{"affineTransform":[1,0,0,1,0,0],"masksToBounds":false,"rotation":0,"scale":1,"position":{"pointX":239.50000000000006,"pointY":117.50000000000003},"width":289,"sublayerTransform":[1,0,0,0,0,1,0,0,0,0,1,0,0,0,0,1],"contentsRect":{"y":0,"x":0,"width":1,"height":1},"opacity":1,"edgeAntialiasingMask":251658240,"height":65,"hidden":false,"anchorPoint":{"pointX":0.5,"pointY":0.5}},"layers":[{"animations":[],"layers":[],"texturedRectangle":{"singleTextureOpacity":1,"textXHeight":0.67607692307692313,"textBaseline":0.9552278958834135,"isBackgroundTexture":true,"isVerticalText":false,"textColor":[0,0,0,1],"textureType":6},"initialState":{"affineTransform":[1,0,0,1,0,0],"masksToBounds":false,"rotation":0,"scale":1,"position":{"pointX":152.49999999999994,"pointY":56.499999999999972},"width":289,"sublayerTransform":[1,0,0,0,0,1,0,0,0,0,1,0,0,0,0,1],"contentsRect":{"y":0,"x":0,"width":1,"height":1},"opacity":1,"edgeAntialiasingMask":0,"height":65,"hidden":false,"anchorPoint":{"pointX":0.5,"pointY":0.5}},"texture":"F70806264CCD7A2CE6EF76B234FDC22B"}]}]},{"animations":[],"initialState":{"affineTransform":[1,0,0,1,0,0],"masksToBounds":false,"rotation":0,"scale":1,"position":{"pointX":960,"pointY":540},"width":1920,"sublayerTransform":[1,0,0,0,0,1,0,0,0,0,1,0,0,0,0,1],"contentsRect":{"y":0,"x":0,"width":1,"height":1},"opacity":1,"edgeAntialiasingMask":251658240,"height":1080,"hidden":false,"anchorPoint":{"pointX":0.5,"pointY":0.5}},"layers":[{"animations":[],"initialState":{"affineTransform":[1,0,0,1,0,0],"masksToBounds":false,"rotation":0,"scale":1,"position":{"pointX":719.9969291687014,"pointY":466.20831298828102},"width":1319.0000000000002,"sublayerTransform":[1,0,0,0,0,1,0,0,0,0,1,0,0,0,0,1],"contentsRect":{"y":0,"x":0,"width":1,"height":1},"opacity":1,"edgeAntialiasingMask":251658240,"height":306,"hidden":false,"anchorPoint":{"pointX":0.5,"pointY":0.5}},"objectID":"980187A1-807D-44E5-BF98-5A56903D5780","layers":[{"animations":[],"layers":[],"texturedRectangle":{"singleTextureOpacity":1,"textXHeight":0.46961805555555558,"textBaseline":0.74317084418402779,"isBackgroundTexture":false,"isVerticalText":false,"textColor":[0.21997910737991333,0.21857796609401703,0.22138024866580963,1],"textureType":6},"initialState":{"affineTransform":[1,0,0,1,0,0],"masksToBounds":false,"rotation":0,"scale":1,"position":{"pointX":643.50307083129871,"pointY":30.291687011718977},"width":1274,"sublayerTransform":[1,0,0,0,0,1,0,0,0,0,1,0,0,0,0,1],"contentsRect":{"y":0,"x":0,"width":1,"height":1},"opacity":1,"edgeAntialiasingMask":0,"height":45,"hidden":false,"anchorPoint":{"pointX":0.5,"pointY":0.5}},"texture":"B27A68FB23B3E8F4E1257CCC1DAB565D"},{"animations":[],"layers":[],"texturedRectangle":{"singleTextureOpacity":1,"textXHeight":0.50316220238095233,"textBaseline":0.75577825875509352,"isBackgroundTexture":false,"isVerticalText":false,"textColor":[0.21997910737991333,0.21857796609401703,0.22138024866580963,1],"textureType":6},"initialState":{"affineTransform":[1,0,0,1,0,0],"masksToBounds":false,"rotation":0,"scale":1,"position":{"pointX":554.00307083129871,"pointY":117.79168701171898},"width":1095,"sublayerTransform":[1,0,0,0,0,1,0,0,0,0,1,0,0,0,0,1],"contentsRect":{"y":0,"x":0,"width":1,"height":1},"opacity":1,"edgeAntialiasingMask":0,"height":42,"hidden":true,"anchorPoint":{"pointX":0.5,"pointY":0.5}},"texture":"C51349F0E43DB4FB3CF1ABCE18B00245"},{"animations":[],"layers":[],"texturedRectangle":{"singleTextureOpacity":1,"textXHeight":0.6037946428571429,"textBaseline":0.9155053070613316,"isBackgroundTexture":false,"isVerticalText":false,"textColor":[0.21997910737991333,0.21857796609401703,0.22138024866580963,1],"textureType":6},"initialState":{"affineTransform":[1,0,0,1,0,0],"masksToBounds":false,"rotation":0,"scale":1,"position":{"pointX":230.50307083129869,"pointY":201.29168701171898},"width":448,"sublayerTransform":[1,0,0,0,0,1,0,0,0,0,1,0,0,0,0,1],"contentsRect":{"y":0,"x":0,"width":1,"height":1},"opacity":1,"edgeAntialiasingMask":0,"height":35,"hidden":true,"anchorPoint":{"pointX":0.5,"pointY":0.5}},"texture":"F119794F38BEBA339B2ADE97DA30ED22"},{"animations":[],"layers":[],"texturedRectangle":{"singleTextureOpacity":1,"textXHeight":0.49146075581395349,"textBaseline":0.75215545643207637,"isBackgroundTexture":false,"isVerticalText":false,"textColor":[0.21997910737991333,0.21857796609401703,0.22138024866580963,1],"textureType":6},"initialState":{"affineTransform":[1,0,0,1,0,0],"masksToBounds":false,"rotation":0,"scale":1,"position":{"pointX":666.00307083129871,"pointY":292.29168701171898},"width":1319,"sublayerTransform":[1,0,0,0,0,1,0,0,0,0,1,0,0,0,0,1],"contentsRect":{"y":0,"x":0,"width":1,"height":1},"opacity":1,"edgeAntialiasingMask":0,"height":43,"hidden":true,"anchorPoint":{"pointX":0.5,"pointY":0.5}},"texture":"08CFE66A480ED77D2CFE6207C3B1E0F5"}]}]},{"animations":[],"initialState":{"affineTransform":[1,0,0,1,0,0],"masksToBounds":false,"rotation":0,"scale":1,"position":{"pointX":960,"pointY":540},"width":1920,"sublayerTransform":[1,0,0,0,0,1,0,0,0,0,1,0,0,0,0,1],"contentsRect":{"y":0,"x":0,"width":1,"height":1},"opacity":1,"edgeAntialiasingMask":251658240,"height":1080,"hidden":false,"anchorPoint":{"pointX":0.5,"pointY":0.5}},"layers":[{"animations":[],"initialState":{"affineTransform":[1,0,0,1,0,0],"masksToBounds":false,"rotation":0,"scale":1,"position":{"pointX":826.45411682128906,"pointY":240.18760621547699},"width":1454,"sublayerTransform":[1,0,0,0,0,1,0,0,0,0,1,0,0,0,0,1],"contentsRect":{"y":0,"x":0,"width":1,"height":1},"opacity":1,"edgeAntialiasingMask":251658240,"height":43,"hidden":false,"anchorPoint":{"pointX":0.5,"pointY":0.5}},"layers":[{"animations":[],"layers":[],"texturedRectangle":{"singleTextureOpacity":1,"textXHeight":0.49146075581395349,"textBaseline":0.76562747012737187,"isBackgroundTexture":true,"isVerticalText":false,"textColor":[0.21997910737991333,0.21857796609401703,0.22138024866580963,1],"textureType":6},"initialState":{"affineTransform":[1,0,0,1,0,0],"masksToBounds":false,"rotation":0,"scale":1,"position":{"pointX":732.54588317871094,"pointY":29.81239378452301},"width":1454,"sublayerTransform":[1,0,0,0,0,1,0,0,0,0,1,0,0,0,0,1],"contentsRect":{"y":0,"x":0,"width":1,"height":1},"opacity":1,"edgeAntialiasingMask":0,"height":43,"hidden":false,"anchorPoint":{"pointX":0.5,"pointY":0.5}},"texture":"5DE7B0CC278EBD77E051848EF72AD393"}]}]},{"animations":[],"initialState":{"affineTransform":[1,0,0,1,0,0],"masksToBounds":false,"rotation":0,"scale":1,"position":{"pointX":960,"pointY":540},"width":1920,"sublayerTransform":[1,0,0,0,0,1,0,0,0,0,1,0,0,0,0,1],"contentsRect":{"y":0,"x":0,"width":1,"height":1},"opacity":1,"edgeAntialiasingMask":251658240,"height":1080,"hidden":false,"anchorPoint":{"pointX":0.5,"pointY":0.5}},"layers":[{"animations":[],"initialState":{"affineTransform":[1,0,0,1,0,0],"masksToBounds":false,"rotation":0,"scale":1,"position":{"pointX":742.04576110839832,"pointY":793.44873046874977},"width":1299,"sublayerTransform":[1,0,0,0,0,1,0,0,0,0,1,0,0,0,0,1],"contentsRect":{"y":0,"x":0,"width":1,"height":1},"opacity":1,"edgeAntialiasingMask":251658240,"height":296,"hidden":false,"anchorPoint":{"pointX":0.5,"pointY":0.5}},"objectID":"0CF4FF1B-C915-4A9D-816F-AAEFF1151945","layers":[{"animations":[],"layers":[],"texturedRectangle":{"singleTextureOpacity":1,"textXHeight":0.048191379856418921,"textBaseline":-0.14375428895692569,"isBackgroundTexture":true,"isVerticalText":false,"textColor":[0.37036359310150146,0.37036353349685669,0.37036359310150146,1],"textureType":6},"initialState":{"affineTransform":[1,0,0,1,0,0],"masksToBounds":false,"rotation":0,"scale":1,"position":{"pointX":650.95423889160168,"pointY":190.55126953125023},"width":1299,"sublayerTransform":[1,0,0,0,0,1,0,0,0,0,1,0,0,0,0,1],"contentsRect":{"y":0,"x":0,"width":1,"height":1},"opacity":1,"edgeAntialiasingMask":0,"height":296,"hidden":true,"anchorPoint":{"pointX":0.5,"pointY":0.5}},"texture":"08B4C58F6D9A95559DC4A3C6C6CDFBCB"}]}]},{"animations":[],"initialState":{"affineTransform":[1,0,0,1,0,0],"masksToBounds":false,"rotation":0,"scale":1,"position":{"pointX":960,"pointY":540},"width":1920,"sublayerTransform":[1,0,0,0,0,1,0,0,0,0,1,0,0,0,0,1],"contentsRect":{"y":0,"x":0,"width":1,"height":1},"opacity":1,"edgeAntialiasingMask":251658240,"height":1080,"hidden":false,"anchorPoint":{"pointX":0.5,"pointY":0.5}},"layers":[{"animations":[],"initialState":{"affineTransform":[1,0,0,1,0,0],"masksToBounds":false,"rotation":0,"scale":1,"position":{"pointX":1748.673583984375,"pointY":1058.1215823888779},"width":273,"sublayerTransform":[1,0,0,0,0,1,0,0,0,0,1,0,0,0,0,1],"contentsRect":{"y":0,"x":0,"width":1,"height":1},"opacity":1,"edgeAntialiasingMask":251658240,"height":23,"hidden":false,"anchorPoint":{"pointX":0.5,"pointY":0.5}},"layers":[{"animations":[],"layers":[],"texturedRectangle":{"singleTextureOpacity":1,"textXHeight":0.45940896739130432,"textBaseline":0.72777260386425513,"isBackgroundTexture":true,"isVerticalText":false,"textColor":[0.83603078126907349,0.83603072166442871,0.83603072166442871,1],"textureType":6},"initialState":{"affineTransform":[1,0,0,1,0,0],"masksToBounds":false,"rotation":0,"scale":1,"position":{"pointX":166.326416015625,"pointY":17.878417611122131},"width":273,"sublayerTransform":[1,0,0,0,0,1,0,0,0,0,1,0,0,0,0,1],"contentsRect":{"y":0,"x":0,"width":1,"height":1},"opacity":1,"edgeAntialiasingMask":0,"height":23,"hidden":false,"anchorPoint":{"pointX":0.5,"pointY":0.5}},"texture":"C1D05F54FBF927BDB7F1A842AC0F0C26"}]}]}]}},{"effects":[{"beginTime":0,"baseLayer":{"animations":[],"initialState":{"affineTransform":[1,0,0,1,0,0],"masksToBounds":false,"rotation":0,"scale":1,"position":{"pointX":719.9969291687014,"pointY":466.20831298828102},"width":1319.0000000000002,"sublayerTransform":[1,0,0,0,0,1,0,0,0,0,1,0,0,0,0,1],"contentsRect":{"y":0,"x":0,"width":1,"height":1},"opacity":1,"edgeAntialiasingMask":251658240,"height":306,"hidden":false,"anchorPoint":{"pointX":0.5,"pointY":0.5}},"objectID":"980187A1-807D-44E5-BF98-5A56903D5780","layers":[{"animations":[],"layers":[],"texturedRectangle":{"singleTextureOpacity":1,"textXHeight":0.46961805555555558,"textBaseline":0.74317084418402779,"isBackgroundTexture":false,"isVerticalText":false,"textColor":[0.21997910737991333,0.21857796609401703,0.22138024866580963,1],"textureType":6},"initialState":{"affineTransform":[1,0,0,1,0,0],"masksToBounds":false,"rotation":0,"scale":1,"position":{"pointX":643.50307083129871,"pointY":30.291687011718977},"width":1274,"sublayerTransform":[1,0,0,0,0,1,0,0,0,0,1,0,0,0,0,1],"contentsRect":{"y":0,"x":0,"width":1,"height":1},"opacity":1,"edgeAntialiasingMask":0,"height":45,"hidden":false,"anchorPoint":{"pointX":0.5,"pointY":0.5}},"texture":"B27A68FB23B3E8F4E1257CCC1DAB565D"},{"animations":[],"layers":[],"texturedRectangle":{"singleTextureOpacity":1,"textXHeight":0.50316220238095233,"textBaseline":0.75577825875509352,"isBackgroundTexture":false,"isVerticalText":false,"textColor":[0.21997910737991333,0.21857796609401703,0.22138024866580963,1],"textureType":6},"initialState":{"affineTransform":[1,0,0,1,0,0],"masksToBounds":false,"rotation":0,"scale":1,"position":{"pointX":554.00307083129871,"pointY":117.79168701171898},"width":1095,"sublayerTransform":[1,0,0,0,0,1,0,0,0,0,1,0,0,0,0,1],"contentsRect":{"y":0,"x":0,"width":1,"height":1},"opacity":1,"edgeAntialiasingMask":0,"height":42,"hidden":false,"anchorPoint":{"pointX":0.5,"pointY":0.5}},"texture":"C51349F0E43DB4FB3CF1ABCE18B00245"},{"animations":[],"initialState":{"affineTransform":[1,0,0,1,0,0],"masksToBounds":false,"rotation":0,"scale":1,"position":{"pointX":899.50307083129871,"pointY":226.79168701171898},"width":1319.0000000000002,"sublayerTransform":[1,0,0,0,0,1,0,0,0,0,1,-0.00035007912466775983,0,0,0,1],"contentsRect":{"y":0,"x":0,"width":1,"height":1},"opacity":1,"edgeAntialiasingMask":251658240,"height":306,"hidden":false,"anchorPoint":{"pointX":0.68195835544450234,"pointY":0.74114930395986589}},"layers":[{"animations":[{"additive":false,"timeOffset":0,"beginTime":1e-100,"repeatCount":0,"fillMode":"both","duration":0.01,"autoreverses":false,"animations":[{"additive":false,"timeOffset":0,"beginTime":0,"from":{"scalar":true},"repeatCount":0,"fillMode":"both","duration":0.0001,"autoreverses":false,"property":"hidden","to":{"scalar":false},"removedOnCompletion":true},{"additive":false,"timeOffset":0,"beginTime":0.0001,"from":{"scalar":false},"repeatCount":0,"fillMode":"forwards","duration":0.0099000000000000008,"autoreverses":false,"property":"hidden","to":{"scalar":false},"removedOnCompletion":true}],"removedOnCompletion":false}],"layers":[],"texturedRectangle":{"singleTextureOpacity":1,"textXHeight":0.6037946428571429,"textBaseline":0.9155053070613316,"isBackgroundTexture":false,"isVerticalText":false,"textColor":[0.21997910737991333,0.21857796609401703,0.22138024866580963,1],"textureType":6},"initialState":{"affineTransform":[1,0,0,1,0,0],"masksToBounds":false,"rotation":0,"scale":1,"position":{"pointX":230.50307083129869,"pointY":201.29168701171898},"width":448,"sublayerTransform":[1,0,0,0,0,1,0,0,0,0,1,0,0,0,0,1],"contentsRect":{"y":0,"x":0,"width":1,"height":1},"opacity":1,"edgeAntialiasingMask":0,"height":35,"hidden":true,"anchorPoint":{"pointX":0.5,"pointY":0.5}},"texture":"F119794F38BEBA339B2ADE97DA30ED22"}]},{"animations":[],"layers":[],"texturedRectangle":{"singleTextureOpacity":1,"textXHeight":0.49146075581395349,"textBaseline":0.75215545643207637,"isBackgroundTexture":false,"isVerticalText":false,"textColor":[0.21997910737991333,0.21857796609401703,0.22138024866580963,1],"textureType":6},"initialState":{"affineTransform":[1,0,0,1,0,0],"masksToBounds":false,"rotation":0,"scale":1,"position":{"pointX":666.00307083129871,"pointY":292.29168701171898},"width":1319,"sublayerTransform":[1,0,0,0,0,1,0,0,0,0,1,0,0,0,0,1],"contentsRect":{"y":0,"x":0,"width":1,"height":1},"opacity":1,"edgeAntialiasingMask":0,"height":43,"hidden":true,"anchorPoint":{"pointX":0.5,"pointY":0.5}},"texture":"08CFE66A480ED77D2CFE6207C3B1E0F5"}]},"effects":[],"duration":0.01,"type":"buildIn","attributes":{"direction":0},"name":"apple:bc-appear","objectID":"980187A1-807D-44E5-BF98-5A56903D5780"}],"automaticPlay":false,"hyperlinks":[],"accessibility":[{"text":"Results","targetRectangle":{"y":89,"x":99,"width":291.80500026598571,"height":100.53440856933594}},{"text":"Alison M. Ashbury, 2022-05-30","targetRectangle":{"y":1050.6215823888779,"x":1643.8827819824219,"width":269.873046875,"height":24}},{"text":"Plainly describe what your data shows (no methods or interpretation)","targetRectangle":{"y":317.20831298828125,"x":110.21121215820312,"width":1231.46484375,"height":47}},{"text":"Figures and Tables as focal points, text builds around these ","targetRectangle":{"y":359.50831186771393,"x":110.21121215820312,"width":1060.09765625,"height":92}},{"text":"What does my audience need to know in order to trust the conclusions of my study?","targetRectangle":{"y":222.68760621547699,"x":103.45411682128906,"width":1452.8125,"height":47}}],"baseLayer":{"animations":[],"initialState":{"affineTransform":[1,0,0,1,0,0],"masksToBounds":false,"rotation":0,"scale":1,"position":{"pointX":960,"pointY":540},"width":1920,"sublayerTransform":[1,0,0,0,0,1,0,0,0,0,1,0,0,0,0,1],"contentsRect":{"y":0,"x":0,"width":1,"height":1},"opacity":1,"edgeAntialiasingMask":251658240,"height":1080,"hidden":false,"anchorPoint":{"pointX":0.5,"pointY":0.5}},"layers":[{"animations":[],"initialState":{"affineTransform":[1,0,0,1,0,0],"masksToBounds":false,"rotation":0,"scale":1,"position":{"pointX":960,"pointY":540},"width":1920,"sublayerTransform":[1,0,0,0,0,1,0,0,0,0,1,0,0,0,0,1],"contentsRect":{"y":0,"x":0,"width":1,"height":1},"opacity":1,"edgeAntialiasingMask":251658240,"height":1080,"hidden":false,"anchorPoint":{"pointX":0.5,"pointY":0.5}},"layers":[{"animations":[],"initialState":{"affineTransform":[1,0,0,1,0,0],"masksToBounds":false,"rotation":0,"scale":1,"position":{"pointX":960,"pointY":540},"width":1920,"sublayerTransform":[1,0,0,0,0,1,0,0,0,0,1,0,0,0,0,1],"contentsRect":{"y":0,"x":0,"width":1,"height":1},"opacity":1,"edgeAntialiasingMask":251658240,"height":1080,"hidden":false,"anchorPoint":{"pointX":0.5,"pointY":0.5}},"layers":[{"animations":[],"layers":[],"texturedRectangle":{"isBackgroundTexture":true,"singleTextureOpacity":1,"textureType":1,"textBaseline":0,"textXHeight":0,"isVerticalText":false},"initialState":{"affineTransform":[1,0,0,1,0,0],"masksToBounds":false,"rotation":0,"scale":1,"position":{"pointX":960,"pointY":540},"width":1920,"sublayerTransform":[1,0,0,0,0,1,0,0,0,0,1,0,0,0,0,1],"contentsRect":{"y":0,"x":0,"width":1,"height":1},"opacity":1,"edgeAntialiasingMask":0,"height":1080,"hidden":false,"anchorPoint":{"pointX":0.5,"pointY":0.5}},"texture":"C25C25FF361FB24FC35F6B120D2F252D"}]}]},{"animations":[],"initialState":{"affineTransform":[1,0,0,1,0,0],"masksToBounds":false,"rotation":0,"scale":1,"position":{"pointX":960,"pointY":540},"width":1920,"sublayerTransform":[1,0,0,0,0,1,0,0,0,0,1,0,0,0,0,1],"contentsRect":{"y":0,"x":0,"width":1,"height":1},"opacity":1,"edgeAntialiasingMask":251658240,"height":1080,"hidden":false,"anchorPoint":{"pointX":0.5,"pointY":0.5}},"layers":[{"animations":[],"initialState":{"affineTransform":[1,0,0,1,0,0],"masksToBounds":false,"rotation":0,"scale":1,"position":{"pointX":239.50000000000006,"pointY":117.50000000000003},"width":289,"sublayerTransform":[1,0,0,0,0,1,0,0,0,0,1,0,0,0,0,1],"contentsRect":{"y":0,"x":0,"width":1,"height":1},"opacity":1,"edgeAntialiasingMask":251658240,"height":65,"hidden":false,"anchorPoint":{"pointX":0.5,"pointY":0.5}},"layers":[{"animations":[],"layers":[],"texturedRectangle":{"singleTextureOpacity":1,"textXHeight":0.67607692307692313,"textBaseline":0.9552278958834135,"isBackgroundTexture":true,"isVerticalText":false,"textColor":[0,0,0,1],"textureType":6},"initialState":{"affineTransform":[1,0,0,1,0,0],"masksToBounds":false,"rotation":0,"scale":1,"position":{"pointX":152.49999999999994,"pointY":56.499999999999972},"width":289,"sublayerTransform":[1,0,0,0,0,1,0,0,0,0,1,0,0,0,0,1],"contentsRect":{"y":0,"x":0,"width":1,"height":1},"opacity":1,"edgeAntialiasingMask":0,"height":65,"hidden":false,"anchorPoint":{"pointX":0.5,"pointY":0.5}},"texture":"F70806264CCD7A2CE6EF76B234FDC22B"}]}]},{"animations":[],"initialState":{"affineTransform":[1,0,0,1,0,0],"masksToBounds":false,"rotation":0,"scale":1,"position":{"pointX":960,"pointY":540},"width":1920,"sublayerTransform":[1,0,0,0,0,1,0,0,0,0,1,0,0,0,0,1],"contentsRect":{"y":0,"x":0,"width":1,"height":1},"opacity":1,"edgeAntialiasingMask":251658240,"height":1080,"hidden":false,"anchorPoint":{"pointX":0.5,"pointY":0.5}},"layers":[{"animations":[],"initialState":{"affineTransform":[1,0,0,1,0,0],"masksToBounds":false,"rotation":0,"scale":1,"position":{"pointX":719.9969291687014,"pointY":466.20831298828102},"width":1319.0000000000002,"sublayerTransform":[1,0,0,0,0,1,0,0,0,0,1,0,0,0,0,1],"contentsRect":{"y":0,"x":0,"width":1,"height":1},"opacity":1,"edgeAntialiasingMask":251658240,"height":306,"hidden":false,"anchorPoint":{"pointX":0.5,"pointY":0.5}},"objectID":"980187A1-807D-44E5-BF98-5A56903D5780","layers":[{"animations":[],"layers":[],"texturedRectangle":{"singleTextureOpacity":1,"textXHeight":0.46961805555555558,"textBaseline":0.74317084418402779,"isBackgroundTexture":false,"isVerticalText":false,"textColor":[0.21997910737991333,0.21857796609401703,0.22138024866580963,1],"textureType":6},"initialState":{"affineTransform":[1,0,0,1,0,0],"masksToBounds":false,"rotation":0,"scale":1,"position":{"pointX":643.50307083129871,"pointY":30.291687011718977},"width":1274,"sublayerTransform":[1,0,0,0,0,1,0,0,0,0,1,0,0,0,0,1],"contentsRect":{"y":0,"x":0,"width":1,"height":1},"opacity":1,"edgeAntialiasingMask":0,"height":45,"hidden":false,"anchorPoint":{"pointX":0.5,"pointY":0.5}},"texture":"B27A68FB23B3E8F4E1257CCC1DAB565D"},{"animations":[],"layers":[],"texturedRectangle":{"singleTextureOpacity":1,"textXHeight":0.50316220238095233,"textBaseline":0.75577825875509352,"isBackgroundTexture":false,"isVerticalText":false,"textColor":[0.21997910737991333,0.21857796609401703,0.22138024866580963,1],"textureType":6},"initialState":{"affineTransform":[1,0,0,1,0,0],"masksToBounds":false,"rotation":0,"scale":1,"position":{"pointX":554.00307083129871,"pointY":117.79168701171898},"width":1095,"sublayerTransform":[1,0,0,0,0,1,0,0,0,0,1,0,0,0,0,1],"contentsRect":{"y":0,"x":0,"width":1,"height":1},"opacity":1,"edgeAntialiasingMask":0,"height":42,"hidden":false,"anchorPoint":{"pointX":0.5,"pointY":0.5}},"texture":"C51349F0E43DB4FB3CF1ABCE18B00245"},{"animations":[],"layers":[],"texturedRectangle":{"singleTextureOpacity":1,"textXHeight":0.6037946428571429,"textBaseline":0.9155053070613316,"isBackgroundTexture":false,"isVerticalText":false,"textColor":[0.21997910737991333,0.21857796609401703,0.22138024866580963,1],"textureType":6},"initialState":{"affineTransform":[1,0,0,1,0,0],"masksToBounds":false,"rotation":0,"scale":1,"position":{"pointX":230.50307083129869,"pointY":201.29168701171898},"width":448,"sublayerTransform":[1,0,0,0,0,1,0,0,0,0,1,0,0,0,0,1],"contentsRect":{"y":0,"x":0,"width":1,"height":1},"opacity":1,"edgeAntialiasingMask":0,"height":35,"hidden":true,"anchorPoint":{"pointX":0.5,"pointY":0.5}},"texture":"F119794F38BEBA339B2ADE97DA30ED22"},{"animations":[],"layers":[],"texturedRectangle":{"singleTextureOpacity":1,"textXHeight":0.49146075581395349,"textBaseline":0.75215545643207637,"isBackgroundTexture":false,"isVerticalText":false,"textColor":[0.21997910737991333,0.21857796609401703,0.22138024866580963,1],"textureType":6},"initialState":{"affineTransform":[1,0,0,1,0,0],"masksToBounds":false,"rotation":0,"scale":1,"position":{"pointX":666.00307083129871,"pointY":292.29168701171898},"width":1319,"sublayerTransform":[1,0,0,0,0,1,0,0,0,0,1,0,0,0,0,1],"contentsRect":{"y":0,"x":0,"width":1,"height":1},"opacity":1,"edgeAntialiasingMask":0,"height":43,"hidden":true,"anchorPoint":{"pointX":0.5,"pointY":0.5}},"texture":"08CFE66A480ED77D2CFE6207C3B1E0F5"}]}]},{"animations":[],"initialState":{"affineTransform":[1,0,0,1,0,0],"masksToBounds":false,"rotation":0,"scale":1,"position":{"pointX":960,"pointY":540},"width":1920,"sublayerTransform":[1,0,0,0,0,1,0,0,0,0,1,0,0,0,0,1],"contentsRect":{"y":0,"x":0,"width":1,"height":1},"opacity":1,"edgeAntialiasingMask":251658240,"height":1080,"hidden":false,"anchorPoint":{"pointX":0.5,"pointY":0.5}},"layers":[{"animations":[],"initialState":{"affineTransform":[1,0,0,1,0,0],"masksToBounds":false,"rotation":0,"scale":1,"position":{"pointX":826.45411682128906,"pointY":240.18760621547699},"width":1454,"sublayerTransform":[1,0,0,0,0,1,0,0,0,0,1,0,0,0,0,1],"contentsRect":{"y":0,"x":0,"width":1,"height":1},"opacity":1,"edgeAntialiasingMask":251658240,"height":43,"hidden":false,"anchorPoint":{"pointX":0.5,"pointY":0.5}},"layers":[{"animations":[],"layers":[],"texturedRectangle":{"singleTextureOpacity":1,"textXHeight":0.49146075581395349,"textBaseline":0.76562747012737187,"isBackgroundTexture":true,"isVerticalText":false,"textColor":[0.21997910737991333,0.21857796609401703,0.22138024866580963,1],"textureType":6},"initialState":{"affineTransform":[1,0,0,1,0,0],"masksToBounds":false,"rotation":0,"scale":1,"position":{"pointX":732.54588317871094,"pointY":29.81239378452301},"width":1454,"sublayerTransform":[1,0,0,0,0,1,0,0,0,0,1,0,0,0,0,1],"contentsRect":{"y":0,"x":0,"width":1,"height":1},"opacity":1,"edgeAntialiasingMask":0,"height":43,"hidden":false,"anchorPoint":{"pointX":0.5,"pointY":0.5}},"texture":"5DE7B0CC278EBD77E051848EF72AD393"}]}]},{"animations":[],"initialState":{"affineTransform":[1,0,0,1,0,0],"masksToBounds":false,"rotation":0,"scale":1,"position":{"pointX":960,"pointY":540},"width":1920,"sublayerTransform":[1,0,0,0,0,1,0,0,0,0,1,0,0,0,0,1],"contentsRect":{"y":0,"x":0,"width":1,"height":1},"opacity":1,"edgeAntialiasingMask":251658240,"height":1080,"hidden":false,"anchorPoint":{"pointX":0.5,"pointY":0.5}},"layers":[{"animations":[],"initialState":{"affineTransform":[1,0,0,1,0,0],"masksToBounds":false,"rotation":0,"scale":1,"position":{"pointX":742.04576110839832,"pointY":793.44873046874977},"width":1299,"sublayerTransform":[1,0,0,0,0,1,0,0,0,0,1,0,0,0,0,1],"contentsRect":{"y":0,"x":0,"width":1,"height":1},"opacity":1,"edgeAntialiasingMask":251658240,"height":296,"hidden":false,"anchorPoint":{"pointX":0.5,"pointY":0.5}},"objectID":"0CF4FF1B-C915-4A9D-816F-AAEFF1151945","layers":[{"animations":[],"layers":[],"texturedRectangle":{"singleTextureOpacity":1,"textXHeight":0.048191379856418921,"textBaseline":-0.14375428895692569,"isBackgroundTexture":true,"isVerticalText":false,"textColor":[0.37036359310150146,0.37036353349685669,0.37036359310150146,1],"textureType":6},"initialState":{"affineTransform":[1,0,0,1,0,0],"masksToBounds":false,"rotation":0,"scale":1,"position":{"pointX":650.95423889160168,"pointY":190.55126953125023},"width":1299,"sublayerTransform":[1,0,0,0,0,1,0,0,0,0,1,0,0,0,0,1],"contentsRect":{"y":0,"x":0,"width":1,"height":1},"opacity":1,"edgeAntialiasingMask":0,"height":296,"hidden":true,"anchorPoint":{"pointX":0.5,"pointY":0.5}},"texture":"08B4C58F6D9A95559DC4A3C6C6CDFBCB"}]}]},{"animations":[],"initialState":{"affineTransform":[1,0,0,1,0,0],"masksToBounds":false,"rotation":0,"scale":1,"position":{"pointX":960,"pointY":540},"width":1920,"sublayerTransform":[1,0,0,0,0,1,0,0,0,0,1,0,0,0,0,1],"contentsRect":{"y":0,"x":0,"width":1,"height":1},"opacity":1,"edgeAntialiasingMask":251658240,"height":1080,"hidden":false,"anchorPoint":{"pointX":0.5,"pointY":0.5}},"layers":[{"animations":[],"initialState":{"affineTransform":[1,0,0,1,0,0],"masksToBounds":false,"rotation":0,"scale":1,"position":{"pointX":1748.673583984375,"pointY":1058.1215823888779},"width":273,"sublayerTransform":[1,0,0,0,0,1,0,0,0,0,1,0,0,0,0,1],"contentsRect":{"y":0,"x":0,"width":1,"height":1},"opacity":1,"edgeAntialiasingMask":251658240,"height":23,"hidden":false,"anchorPoint":{"pointX":0.5,"pointY":0.5}},"layers":[{"animations":[],"layers":[],"texturedRectangle":{"singleTextureOpacity":1,"textXHeight":0.45940896739130432,"textBaseline":0.72777260386425513,"isBackgroundTexture":true,"isVerticalText":false,"textColor":[0.83603078126907349,0.83603072166442871,0.83603072166442871,1],"textureType":6},"initialState":{"affineTransform":[1,0,0,1,0,0],"masksToBounds":false,"rotation":0,"scale":1,"position":{"pointX":166.326416015625,"pointY":17.878417611122131},"width":273,"sublayerTransform":[1,0,0,0,0,1,0,0,0,0,1,0,0,0,0,1],"contentsRect":{"y":0,"x":0,"width":1,"height":1},"opacity":1,"edgeAntialiasingMask":0,"height":23,"hidden":false,"anchorPoint":{"pointX":0.5,"pointY":0.5}},"texture":"C1D05F54FBF927BDB7F1A842AC0F0C26"}]}]}]}},{"effects":[{"beginTime":0,"baseLayer":{"animations":[],"initialState":{"affineTransform":[1,0,0,1,0,0],"masksToBounds":false,"rotation":0,"scale":1,"position":{"pointX":719.9969291687014,"pointY":466.20831298828102},"width":1319.0000000000002,"sublayerTransform":[1,0,0,0,0,1,0,0,0,0,1,0,0,0,0,1],"contentsRect":{"y":0,"x":0,"width":1,"height":1},"opacity":1,"edgeAntialiasingMask":251658240,"height":306,"hidden":false,"anchorPoint":{"pointX":0.5,"pointY":0.5}},"objectID":"980187A1-807D-44E5-BF98-5A56903D5780","layers":[{"animations":[],"layers":[],"texturedRectangle":{"singleTextureOpacity":1,"textXHeight":0.46961805555555558,"textBaseline":0.74317084418402779,"isBackgroundTexture":false,"isVerticalText":false,"textColor":[0.21997910737991333,0.21857796609401703,0.22138024866580963,1],"textureType":6},"initialState":{"affineTransform":[1,0,0,1,0,0],"masksToBounds":false,"rotation":0,"scale":1,"position":{"pointX":643.50307083129871,"pointY":30.291687011718977},"width":1274,"sublayerTransform":[1,0,0,0,0,1,0,0,0,0,1,0,0,0,0,1],"contentsRect":{"y":0,"x":0,"width":1,"height":1},"opacity":1,"edgeAntialiasingMask":0,"height":45,"hidden":false,"anchorPoint":{"pointX":0.5,"pointY":0.5}},"texture":"B27A68FB23B3E8F4E1257CCC1DAB565D"},{"animations":[],"layers":[],"texturedRectangle":{"singleTextureOpacity":1,"textXHeight":0.50316220238095233,"textBaseline":0.75577825875509352,"isBackgroundTexture":false,"isVerticalText":false,"textColor":[0.21997910737991333,0.21857796609401703,0.22138024866580963,1],"textureType":6},"initialState":{"affineTransform":[1,0,0,1,0,0],"masksToBounds":false,"rotation":0,"scale":1,"position":{"pointX":554.00307083129871,"pointY":117.79168701171898},"width":1095,"sublayerTransform":[1,0,0,0,0,1,0,0,0,0,1,0,0,0,0,1],"contentsRect":{"y":0,"x":0,"width":1,"height":1},"opacity":1,"edgeAntialiasingMask":0,"height":42,"hidden":false,"anchorPoint":{"pointX":0.5,"pointY":0.5}},"texture":"C51349F0E43DB4FB3CF1ABCE18B00245"},{"animations":[],"layers":[],"texturedRectangle":{"singleTextureOpacity":1,"textXHeight":0.6037946428571429,"textBaseline":0.9155053070613316,"isBackgroundTexture":false,"isVerticalText":false,"textColor":[0.21997910737991333,0.21857796609401703,0.22138024866580963,1],"textureType":6},"initialState":{"affineTransform":[1,0,0,1,0,0],"masksToBounds":false,"rotation":0,"scale":1,"position":{"pointX":230.50307083129869,"pointY":201.29168701171898},"width":448,"sublayerTransform":[1,0,0,0,0,1,0,0,0,0,1,0,0,0,0,1],"contentsRect":{"y":0,"x":0,"width":1,"height":1},"opacity":1,"edgeAntialiasingMask":0,"height":35,"hidden":false,"anchorPoint":{"pointX":0.5,"pointY":0.5}},"texture":"F119794F38BEBA339B2ADE97DA30ED22"},{"animations":[],"initialState":{"affineTransform":[1,0,0,1,0,0],"masksToBounds":false,"rotation":0,"scale":1,"position":{"pointX":899.50307083129871,"pointY":226.79168701171898},"width":1319.0000000000002,"sublayerTransform":[1,0,0,0,0,1,0,0,0,0,1,-0.00035007912466775983,0,0,0,1],"contentsRect":{"y":0,"x":0,"width":1,"height":1},"opacity":1,"edgeAntialiasingMask":251658240,"height":306,"hidden":false,"anchorPoint":{"pointX":0.68195835544450234,"pointY":0.74114930395986589}},"layers":[{"animations":[{"additive":false,"timeOffset":0,"beginTime":1e-100,"repeatCount":0,"fillMode":"both","duration":0.01,"autoreverses":false,"animations":[{"additive":false,"timeOffset":0,"beginTime":0,"from":{"scalar":true},"repeatCount":0,"fillMode":"both","duration":0.0001,"autoreverses":false,"property":"hidden","to":{"scalar":false},"removedOnCompletion":true},{"additive":false,"timeOffset":0,"beginTime":0.0001,"from":{"scalar":false},"repeatCount":0,"fillMode":"forwards","duration":0.0099000000000000008,"autoreverses":false,"property":"hidden","to":{"scalar":false},"removedOnCompletion":true}],"removedOnCompletion":false}],"layers":[],"texturedRectangle":{"singleTextureOpacity":1,"textXHeight":0.49146075581395349,"textBaseline":0.75215545643207637,"isBackgroundTexture":false,"isVerticalText":false,"textColor":[0.21997910737991333,0.21857796609401703,0.22138024866580963,1],"textureType":6},"initialState":{"affineTransform":[1,0,0,1,0,0],"masksToBounds":false,"rotation":0,"scale":1,"position":{"pointX":666.00307083129871,"pointY":292.29168701171898},"width":1319,"sublayerTransform":[1,0,0,0,0,1,0,0,0,0,1,0,0,0,0,1],"contentsRect":{"y":0,"x":0,"width":1,"height":1},"opacity":1,"edgeAntialiasingMask":0,"height":43,"hidden":true,"anchorPoint":{"pointX":0.5,"pointY":0.5}},"texture":"08CFE66A480ED77D2CFE6207C3B1E0F5"}]}]},"effects":[],"duration":0.01,"type":"buildIn","attributes":{"direction":0},"name":"apple:bc-appear","objectID":"980187A1-807D-44E5-BF98-5A56903D5780"}],"automaticPlay":false,"hyperlinks":[],"accessibility":[{"text":"Results","targetRectangle":{"y":89,"x":99,"width":291.80500026598571,"height":100.53440856933594}},{"text":"Alison M. Ashbury, 2022-05-30","targetRectangle":{"y":1050.6215823888779,"x":1643.8827819824219,"width":269.873046875,"height":24}},{"text":"What does my audience need to know in order to trust the conclusions of my study?","targetRectangle":{"y":222.68760621547699,"x":103.45411682128906,"width":1452.8125,"height":47}}],"baseLayer":{"animations":[],"initialState":{"affineTransform":[1,0,0,1,0,0],"masksToBounds":false,"rotation":0,"scale":1,"position":{"pointX":960,"pointY":540},"width":1920,"sublayerTransform":[1,0,0,0,0,1,0,0,0,0,1,0,0,0,0,1],"contentsRect":{"y":0,"x":0,"width":1,"height":1},"opacity":1,"edgeAntialiasingMask":251658240,"height":1080,"hidden":false,"anchorPoint":{"pointX":0.5,"pointY":0.5}},"layers":[{"animations":[],"initialState":{"affineTransform":[1,0,0,1,0,0],"masksToBounds":false,"rotation":0,"scale":1,"position":{"pointX":960,"pointY":540},"width":1920,"sublayerTransform":[1,0,0,0,0,1,0,0,0,0,1,0,0,0,0,1],"contentsRect":{"y":0,"x":0,"width":1,"height":1},"opacity":1,"edgeAntialiasingMask":251658240,"height":1080,"hidden":false,"anchorPoint":{"pointX":0.5,"pointY":0.5}},"layers":[{"animations":[],"initialState":{"affineTransform":[1,0,0,1,0,0],"masksToBounds":false,"rotation":0,"scale":1,"position":{"pointX":960,"pointY":540},"width":1920,"sublayerTransform":[1,0,0,0,0,1,0,0,0,0,1,0,0,0,0,1],"contentsRect":{"y":0,"x":0,"width":1,"height":1},"opacity":1,"edgeAntialiasingMask":251658240,"height":1080,"hidden":false,"anchorPoint":{"pointX":0.5,"pointY":0.5}},"layers":[{"animations":[],"layers":[],"texturedRectangle":{"isBackgroundTexture":true,"singleTextureOpacity":1,"textureType":1,"textBaseline":0,"textXHeight":0,"isVerticalText":false},"initialState":{"affineTransform":[1,0,0,1,0,0],"masksToBounds":false,"rotation":0,"scale":1,"position":{"pointX":960,"pointY":540},"width":1920,"sublayerTransform":[1,0,0,0,0,1,0,0,0,0,1,0,0,0,0,1],"contentsRect":{"y":0,"x":0,"width":1,"height":1},"opacity":1,"edgeAntialiasingMask":0,"height":1080,"hidden":false,"anchorPoint":{"pointX":0.5,"pointY":0.5}},"texture":"C25C25FF361FB24FC35F6B120D2F252D"}]}]},{"animations":[],"initialState":{"affineTransform":[1,0,0,1,0,0],"masksToBounds":false,"rotation":0,"scale":1,"position":{"pointX":960,"pointY":540},"width":1920,"sublayerTransform":[1,0,0,0,0,1,0,0,0,0,1,0,0,0,0,1],"contentsRect":{"y":0,"x":0,"width":1,"height":1},"opacity":1,"edgeAntialiasingMask":251658240,"height":1080,"hidden":false,"anchorPoint":{"pointX":0.5,"pointY":0.5}},"layers":[{"animations":[],"initialState":{"affineTransform":[1,0,0,1,0,0],"masksToBounds":false,"rotation":0,"scale":1,"position":{"pointX":239.50000000000006,"pointY":117.50000000000003},"width":289,"sublayerTransform":[1,0,0,0,0,1,0,0,0,0,1,0,0,0,0,1],"contentsRect":{"y":0,"x":0,"width":1,"height":1},"opacity":1,"edgeAntialiasingMask":251658240,"height":65,"hidden":false,"anchorPoint":{"pointX":0.5,"pointY":0.5}},"layers":[{"animations":[],"layers":[],"texturedRectangle":{"singleTextureOpacity":1,"textXHeight":0.67607692307692313,"textBaseline":0.9552278958834135,"isBackgroundTexture":true,"isVerticalText":false,"textColor":[0,0,0,1],"textureType":6},"initialState":{"affineTransform":[1,0,0,1,0,0],"masksToBounds":false,"rotation":0,"scale":1,"position":{"pointX":152.49999999999994,"pointY":56.499999999999972},"width":289,"sublayerTransform":[1,0,0,0,0,1,0,0,0,0,1,0,0,0,0,1],"contentsRect":{"y":0,"x":0,"width":1,"height":1},"opacity":1,"edgeAntialiasingMask":0,"height":65,"hidden":false,"anchorPoint":{"pointX":0.5,"pointY":0.5}},"texture":"F70806264CCD7A2CE6EF76B234FDC22B"}]}]},{"animations":[],"initialState":{"affineTransform":[1,0,0,1,0,0],"masksToBounds":false,"rotation":0,"scale":1,"position":{"pointX":960,"pointY":540},"width":1920,"sublayerTransform":[1,0,0,0,0,1,0,0,0,0,1,0,0,0,0,1],"contentsRect":{"y":0,"x":0,"width":1,"height":1},"opacity":1,"edgeAntialiasingMask":251658240,"height":1080,"hidden":false,"anchorPoint":{"pointX":0.5,"pointY":0.5}},"layers":[{"animations":[],"initialState":{"affineTransform":[1,0,0,1,0,0],"masksToBounds":false,"rotation":0,"scale":1,"position":{"pointX":719.9969291687014,"pointY":466.20831298828102},"width":1319.0000000000002,"sublayerTransform":[1,0,0,0,0,1,0,0,0,0,1,0,0,0,0,1],"contentsRect":{"y":0,"x":0,"width":1,"height":1},"opacity":1,"edgeAntialiasingMask":251658240,"height":306,"hidden":false,"anchorPoint":{"pointX":0.5,"pointY":0.5}},"objectID":"980187A1-807D-44E5-BF98-5A56903D5780","layers":[{"animations":[],"layers":[],"texturedRectangle":{"singleTextureOpacity":1,"textXHeight":0.46961805555555558,"textBaseline":0.74317084418402779,"isBackgroundTexture":false,"isVerticalText":false,"textColor":[0.21997910737991333,0.21857796609401703,0.22138024866580963,1],"textureType":6},"initialState":{"affineTransform":[1,0,0,1,0,0],"masksToBounds":false,"rotation":0,"scale":1,"position":{"pointX":643.50307083129871,"pointY":30.291687011718977},"width":1274,"sublayerTransform":[1,0,0,0,0,1,0,0,0,0,1,0,0,0,0,1],"contentsRect":{"y":0,"x":0,"width":1,"height":1},"opacity":1,"edgeAntialiasingMask":0,"height":45,"hidden":false,"anchorPoint":{"pointX":0.5,"pointY":0.5}},"texture":"B27A68FB23B3E8F4E1257CCC1DAB565D"},{"animations":[],"layers":[],"texturedRectangle":{"singleTextureOpacity":1,"textXHeight":0.50316220238095233,"textBaseline":0.75577825875509352,"isBackgroundTexture":false,"isVerticalText":false,"textColor":[0.21997910737991333,0.21857796609401703,0.22138024866580963,1],"textureType":6},"initialState":{"affineTransform":[1,0,0,1,0,0],"masksToBounds":false,"rotation":0,"scale":1,"position":{"pointX":554.00307083129871,"pointY":117.79168701171898},"width":1095,"sublayerTransform":[1,0,0,0,0,1,0,0,0,0,1,0,0,0,0,1],"contentsRect":{"y":0,"x":0,"width":1,"height":1},"opacity":1,"edgeAntialiasingMask":0,"height":42,"hidden":false,"anchorPoint":{"pointX":0.5,"pointY":0.5}},"texture":"C51349F0E43DB4FB3CF1ABCE18B00245"},{"animations":[],"layers":[],"texturedRectangle":{"singleTextureOpacity":1,"textXHeight":0.6037946428571429,"textBaseline":0.9155053070613316,"isBackgroundTexture":false,"isVerticalText":false,"textColor":[0.21997910737991333,0.21857796609401703,0.22138024866580963,1],"textureType":6},"initialState":{"affineTransform":[1,0,0,1,0,0],"masksToBounds":false,"rotation":0,"scale":1,"position":{"pointX":230.50307083129869,"pointY":201.29168701171898},"width":448,"sublayerTransform":[1,0,0,0,0,1,0,0,0,0,1,0,0,0,0,1],"contentsRect":{"y":0,"x":0,"width":1,"height":1},"opacity":1,"edgeAntialiasingMask":0,"height":35,"hidden":false,"anchorPoint":{"pointX":0.5,"pointY":0.5}},"texture":"F119794F38BEBA339B2ADE97DA30ED22"},{"animations":[],"layers":[],"texturedRectangle":{"singleTextureOpacity":1,"textXHeight":0.49146075581395349,"textBaseline":0.75215545643207637,"isBackgroundTexture":false,"isVerticalText":false,"textColor":[0.21997910737991333,0.21857796609401703,0.22138024866580963,1],"textureType":6},"initialState":{"affineTransform":[1,0,0,1,0,0],"masksToBounds":false,"rotation":0,"scale":1,"position":{"pointX":666.00307083129871,"pointY":292.29168701171898},"width":1319,"sublayerTransform":[1,0,0,0,0,1,0,0,0,0,1,0,0,0,0,1],"contentsRect":{"y":0,"x":0,"width":1,"height":1},"opacity":1,"edgeAntialiasingMask":0,"height":43,"hidden":true,"anchorPoint":{"pointX":0.5,"pointY":0.5}},"texture":"08CFE66A480ED77D2CFE6207C3B1E0F5"}]}]},{"animations":[],"initialState":{"affineTransform":[1,0,0,1,0,0],"masksToBounds":false,"rotation":0,"scale":1,"position":{"pointX":960,"pointY":540},"width":1920,"sublayerTransform":[1,0,0,0,0,1,0,0,0,0,1,0,0,0,0,1],"contentsRect":{"y":0,"x":0,"width":1,"height":1},"opacity":1,"edgeAntialiasingMask":251658240,"height":1080,"hidden":false,"anchorPoint":{"pointX":0.5,"pointY":0.5}},"layers":[{"animations":[],"initialState":{"affineTransform":[1,0,0,1,0,0],"masksToBounds":false,"rotation":0,"scale":1,"position":{"pointX":826.45411682128906,"pointY":240.18760621547699},"width":1454,"sublayerTransform":[1,0,0,0,0,1,0,0,0,0,1,0,0,0,0,1],"contentsRect":{"y":0,"x":0,"width":1,"height":1},"opacity":1,"edgeAntialiasingMask":251658240,"height":43,"hidden":false,"anchorPoint":{"pointX":0.5,"pointY":0.5}},"layers":[{"animations":[],"layers":[],"texturedRectangle":{"singleTextureOpacity":1,"textXHeight":0.49146075581395349,"textBaseline":0.76562747012737187,"isBackgroundTexture":true,"isVerticalText":false,"textColor":[0.21997910737991333,0.21857796609401703,0.22138024866580963,1],"textureType":6},"initialState":{"affineTransform":[1,0,0,1,0,0],"masksToBounds":false,"rotation":0,"scale":1,"position":{"pointX":732.54588317871094,"pointY":29.81239378452301},"width":1454,"sublayerTransform":[1,0,0,0,0,1,0,0,0,0,1,0,0,0,0,1],"contentsRect":{"y":0,"x":0,"width":1,"height":1},"opacity":1,"edgeAntialiasingMask":0,"height":43,"hidden":false,"anchorPoint":{"pointX":0.5,"pointY":0.5}},"texture":"5DE7B0CC278EBD77E051848EF72AD393"}]}]},{"animations":[],"initialState":{"affineTransform":[1,0,0,1,0,0],"masksToBounds":false,"rotation":0,"scale":1,"position":{"pointX":960,"pointY":540},"width":1920,"sublayerTransform":[1,0,0,0,0,1,0,0,0,0,1,0,0,0,0,1],"contentsRect":{"y":0,"x":0,"width":1,"height":1},"opacity":1,"edgeAntialiasingMask":251658240,"height":1080,"hidden":false,"anchorPoint":{"pointX":0.5,"pointY":0.5}},"layers":[{"animations":[],"initialState":{"affineTransform":[1,0,0,1,0,0],"masksToBounds":false,"rotation":0,"scale":1,"position":{"pointX":742.04576110839832,"pointY":793.44873046874977},"width":1299,"sublayerTransform":[1,0,0,0,0,1,0,0,0,0,1,0,0,0,0,1],"contentsRect":{"y":0,"x":0,"width":1,"height":1},"opacity":1,"edgeAntialiasingMask":251658240,"height":296,"hidden":false,"anchorPoint":{"pointX":0.5,"pointY":0.5}},"objectID":"0CF4FF1B-C915-4A9D-816F-AAEFF1151945","layers":[{"animations":[],"layers":[],"texturedRectangle":{"singleTextureOpacity":1,"textXHeight":0.048191379856418921,"textBaseline":-0.14375428895692569,"isBackgroundTexture":true,"isVerticalText":false,"textColor":[0.37036359310150146,0.37036353349685669,0.37036359310150146,1],"textureType":6},"initialState":{"affineTransform":[1,0,0,1,0,0],"masksToBounds":false,"rotation":0,"scale":1,"position":{"pointX":650.95423889160168,"pointY":190.55126953125023},"width":1299,"sublayerTransform":[1,0,0,0,0,1,0,0,0,0,1,0,0,0,0,1],"contentsRect":{"y":0,"x":0,"width":1,"height":1},"opacity":1,"edgeAntialiasingMask":0,"height":296,"hidden":true,"anchorPoint":{"pointX":0.5,"pointY":0.5}},"texture":"08B4C58F6D9A95559DC4A3C6C6CDFBCB"}]}]},{"animations":[],"initialState":{"affineTransform":[1,0,0,1,0,0],"masksToBounds":false,"rotation":0,"scale":1,"position":{"pointX":960,"pointY":540},"width":1920,"sublayerTransform":[1,0,0,0,0,1,0,0,0,0,1,0,0,0,0,1],"contentsRect":{"y":0,"x":0,"width":1,"height":1},"opacity":1,"edgeAntialiasingMask":251658240,"height":1080,"hidden":false,"anchorPoint":{"pointX":0.5,"pointY":0.5}},"layers":[{"animations":[],"initialState":{"affineTransform":[1,0,0,1,0,0],"masksToBounds":false,"rotation":0,"scale":1,"position":{"pointX":1748.673583984375,"pointY":1058.1215823888779},"width":273,"sublayerTransform":[1,0,0,0,0,1,0,0,0,0,1,0,0,0,0,1],"contentsRect":{"y":0,"x":0,"width":1,"height":1},"opacity":1,"edgeAntialiasingMask":251658240,"height":23,"hidden":false,"anchorPoint":{"pointX":0.5,"pointY":0.5}},"layers":[{"animations":[],"layers":[],"texturedRectangle":{"singleTextureOpacity":1,"textXHeight":0.45940896739130432,"textBaseline":0.72777260386425513,"isBackgroundTexture":true,"isVerticalText":false,"textColor":[0.83603078126907349,0.83603072166442871,0.83603072166442871,1],"textureType":6},"initialState":{"affineTransform":[1,0,0,1,0,0],"masksToBounds":false,"rotation":0,"scale":1,"position":{"pointX":166.326416015625,"pointY":17.878417611122131},"width":273,"sublayerTransform":[1,0,0,0,0,1,0,0,0,0,1,0,0,0,0,1],"contentsRect":{"y":0,"x":0,"width":1,"height":1},"opacity":1,"edgeAntialiasingMask":0,"height":23,"hidden":false,"anchorPoint":{"pointX":0.5,"pointY":0.5}},"texture":"C1D05F54FBF927BDB7F1A842AC0F0C26"}]}]}]}},{"effects":[{"beginTime":0,"baseLayer":{"animations":[],"initialState":{"affineTransform":[1,0,0,1,0,0],"masksToBounds":false,"rotation":0,"scale":1,"position":{"pointX":742.04576110839832,"pointY":793.44873046874977},"width":1299,"sublayerTransform":[1,0,0,0,0,1,0,0,0,0,1,0,0,0,0,1],"contentsRect":{"y":0,"x":0,"width":1,"height":1},"opacity":1,"edgeAntialiasingMask":251658240,"height":296,"hidden":false,"anchorPoint":{"pointX":0.5,"pointY":0.5}},"objectID":"0CF4FF1B-C915-4A9D-816F-AAEFF1151945","layers":[{"animations":[],"initialState":{"affineTransform":[1,0,0,1,0,0],"masksToBounds":false,"rotation":0,"scale":1,"position":{"pointX":867.45423889160168,"pointY":-105.44873046874977},"width":1299,"sublayerTransform":[1,0,0,0,0,1,0,0,0,0,1,-0.00035007912466775983,0,0,0,1],"contentsRect":{"y":0,"x":0,"width":1,"height":1},"opacity":1,"edgeAntialiasingMask":251658240,"height":296,"hidden":false,"anchorPoint":{"pointX":0.66778617312671418,"pointY":-0.35624571104307357}},"layers":[{"animations":[{"additive":false,"timeOffset":0,"beginTime":1e-100,"repeatCount":0,"fillMode":"both","duration":0.01,"autoreverses":false,"animations":[{"additive":false,"timeOffset":0,"beginTime":0,"from":{"scalar":true},"repeatCount":0,"fillMode":"both","duration":0.0001,"autoreverses":false,"property":"hidden","to":{"scalar":false},"removedOnCompletion":true},{"additive":false,"timeOffset":0,"beginTime":0.0001,"from":{"scalar":false},"repeatCount":0,"fillMode":"forwards","duration":0.0099000000000000008,"autoreverses":false,"property":"hidden","to":{"scalar":false},"removedOnCompletion":true}],"removedOnCompletion":false}],"layers":[],"texturedRectangle":{"singleTextureOpacity":1,"textXHeight":0.048191379856418921,"textBaseline":-0.14375428895692569,"isBackgroundTexture":true,"isVerticalText":false,"textColor":[0.37036359310150146,0.37036353349685669,0.37036359310150146,1],"textureType":6},"initialState":{"affineTransform":[1,0,0,1,0,0],"masksToBounds":false,"rotation":0,"scale":1,"position":{"pointX":650.95423889160168,"pointY":190.55126953125023},"width":1299,"sublayerTransform":[1,0,0,0,0,1,0,0,0,0,1,0,0,0,0,1],"contentsRect":{"y":0,"x":0,"width":1,"height":1},"opacity":1,"edgeAntialiasingMask":0,"height":296,"hidden":true,"anchorPoint":{"pointX":0.5,"pointY":0.5}},"texture":"08B4C58F6D9A95559DC4A3C6C6CDFBCB"}]}]},"effects":[],"duration":0.01,"type":"buildIn","attributes":{"direction":0},"name":"apple:bc-appear","objectID":"0CF4FF1B-C915-4A9D-816F-AAEFF1151945"}],"automaticPlay":false,"hyperlinks":[],"accessibility":[{"text":"Results","targetRectangle":{"y":89,"x":99,"width":291.80500026598571,"height":100.53440856933594}},{"text":"Alison M. Ashbury, 2022-05-30","targetRectangle":{"y":1050.6215823888779,"x":1643.8827819824219,"width":269.873046875,"height":24}},{"text":"Plainly describe what your data shows (no methods or interpretation)","targetRectangle":{"y":317.20831298828125,"x":110.21121215820312,"width":1231.46484375,"height":47}},{"text":"Figures and Tables as focal points, text builds around these ","targetRectangle":{"y":359.50831186771393,"x":110.21121215820312,"width":1060.09765625,"height":92}},{"text":"Break into subsections","targetRectangle":{"y":446.80831074714661,"x":110.21121215820312,"width":404.51171875,"height":92}},{"text":"Use appropriate technical language, include necessary statsy numbers","targetRectangle":{"y":534.10830962657928,"x":110.21121215820312,"width":1275.37109375,"height":92}},{"text":"What does my audience need to know in order to trust the conclusions of my study?","targetRectangle":{"y":222.68760621547699,"x":103.45411682128906,"width":1452.8125,"height":47}}],"baseLayer":{"animations":[],"initialState":{"affineTransform":[1,0,0,1,0,0],"masksToBounds":false,"rotation":0,"scale":1,"position":{"pointX":960,"pointY":540},"width":1920,"sublayerTransform":[1,0,0,0,0,1,0,0,0,0,1,0,0,0,0,1],"contentsRect":{"y":0,"x":0,"width":1,"height":1},"opacity":1,"edgeAntialiasingMask":251658240,"height":1080,"hidden":false,"anchorPoint":{"pointX":0.5,"pointY":0.5}},"layers":[{"animations":[],"initialState":{"affineTransform":[1,0,0,1,0,0],"masksToBounds":false,"rotation":0,"scale":1,"position":{"pointX":960,"pointY":540},"width":1920,"sublayerTransform":[1,0,0,0,0,1,0,0,0,0,1,0,0,0,0,1],"contentsRect":{"y":0,"x":0,"width":1,"height":1},"opacity":1,"edgeAntialiasingMask":251658240,"height":1080,"hidden":false,"anchorPoint":{"pointX":0.5,"pointY":0.5}},"layers":[{"animations":[],"initialState":{"affineTransform":[1,0,0,1,0,0],"masksToBounds":false,"rotation":0,"scale":1,"position":{"pointX":960,"pointY":540},"width":1920,"sublayerTransform":[1,0,0,0,0,1,0,0,0,0,1,0,0,0,0,1],"contentsRect":{"y":0,"x":0,"width":1,"height":1},"opacity":1,"edgeAntialiasingMask":251658240,"height":1080,"hidden":false,"anchorPoint":{"pointX":0.5,"pointY":0.5}},"layers":[{"animations":[],"layers":[],"texturedRectangle":{"isBackgroundTexture":true,"singleTextureOpacity":1,"textureType":1,"textBaseline":0,"textXHeight":0,"isVerticalText":false},"initialState":{"affineTransform":[1,0,0,1,0,0],"masksToBounds":false,"rotation":0,"scale":1,"position":{"pointX":960,"pointY":540},"width":1920,"sublayerTransform":[1,0,0,0,0,1,0,0,0,0,1,0,0,0,0,1],"contentsRect":{"y":0,"x":0,"width":1,"height":1},"opacity":1,"edgeAntialiasingMask":0,"height":1080,"hidden":false,"anchorPoint":{"pointX":0.5,"pointY":0.5}},"texture":"C25C25FF361FB24FC35F6B120D2F252D"}]}]},{"animations":[],"initialState":{"affineTransform":[1,0,0,1,0,0],"masksToBounds":false,"rotation":0,"scale":1,"position":{"pointX":960,"pointY":540},"width":1920,"sublayerTransform":[1,0,0,0,0,1,0,0,0,0,1,0,0,0,0,1],"contentsRect":{"y":0,"x":0,"width":1,"height":1},"opacity":1,"edgeAntialiasingMask":251658240,"height":1080,"hidden":false,"anchorPoint":{"pointX":0.5,"pointY":0.5}},"layers":[{"animations":[],"initialState":{"affineTransform":[1,0,0,1,0,0],"masksToBounds":false,"rotation":0,"scale":1,"position":{"pointX":239.50000000000006,"pointY":117.50000000000003},"width":289,"sublayerTransform":[1,0,0,0,0,1,0,0,0,0,1,0,0,0,0,1],"contentsRect":{"y":0,"x":0,"width":1,"height":1},"opacity":1,"edgeAntialiasingMask":251658240,"height":65,"hidden":false,"anchorPoint":{"pointX":0.5,"pointY":0.5}},"layers":[{"animations":[],"layers":[],"texturedRectangle":{"singleTextureOpacity":1,"textXHeight":0.67607692307692313,"textBaseline":0.9552278958834135,"isBackgroundTexture":true,"isVerticalText":false,"textColor":[0,0,0,1],"textureType":6},"initialState":{"affineTransform":[1,0,0,1,0,0],"masksToBounds":false,"rotation":0,"scale":1,"position":{"pointX":152.49999999999994,"pointY":56.499999999999972},"width":289,"sublayerTransform":[1,0,0,0,0,1,0,0,0,0,1,0,0,0,0,1],"contentsRect":{"y":0,"x":0,"width":1,"height":1},"opacity":1,"edgeAntialiasingMask":0,"height":65,"hidden":false,"anchorPoint":{"pointX":0.5,"pointY":0.5}},"texture":"F70806264CCD7A2CE6EF76B234FDC22B"}]}]},{"animations":[],"initialState":{"affineTransform":[1,0,0,1,0,0],"masksToBounds":false,"rotation":0,"scale":1,"position":{"pointX":960,"pointY":540},"width":1920,"sublayerTransform":[1,0,0,0,0,1,0,0,0,0,1,0,0,0,0,1],"contentsRect":{"y":0,"x":0,"width":1,"height":1},"opacity":1,"edgeAntialiasingMask":251658240,"height":1080,"hidden":false,"anchorPoint":{"pointX":0.5,"pointY":0.5}},"layers":[{"animations":[],"initialState":{"affineTransform":[1,0,0,1,0,0],"masksToBounds":false,"rotation":0,"scale":1,"position":{"pointX":719.9969291687014,"pointY":466.20831298828102},"width":1319.0000000000002,"sublayerTransform":[1,0,0,0,0,1,0,0,0,0,1,0,0,0,0,1],"contentsRect":{"y":0,"x":0,"width":1,"height":1},"opacity":1,"edgeAntialiasingMask":251658240,"height":306,"hidden":false,"anchorPoint":{"pointX":0.5,"pointY":0.5}},"objectID":"980187A1-807D-44E5-BF98-5A56903D5780","layers":[{"animations":[],"layers":[],"texturedRectangle":{"singleTextureOpacity":1,"textXHeight":0.46961805555555558,"textBaseline":0.74317084418402779,"isBackgroundTexture":false,"isVerticalText":false,"textColor":[0.21997910737991333,0.21857796609401703,0.22138024866580963,1],"textureType":6},"initialState":{"affineTransform":[1,0,0,1,0,0],"masksToBounds":false,"rotation":0,"scale":1,"position":{"pointX":643.50307083129871,"pointY":30.291687011718977},"width":1274,"sublayerTransform":[1,0,0,0,0,1,0,0,0,0,1,0,0,0,0,1],"contentsRect":{"y":0,"x":0,"width":1,"height":1},"opacity":1,"edgeAntialiasingMask":0,"height":45,"hidden":false,"anchorPoint":{"pointX":0.5,"pointY":0.5}},"texture":"B27A68FB23B3E8F4E1257CCC1DAB565D"},{"animations":[],"layers":[],"texturedRectangle":{"singleTextureOpacity":1,"textXHeight":0.50316220238095233,"textBaseline":0.75577825875509352,"isBackgroundTexture":false,"isVerticalText":false,"textColor":[0.21997910737991333,0.21857796609401703,0.22138024866580963,1],"textureType":6},"initialState":{"affineTransform":[1,0,0,1,0,0],"masksToBounds":false,"rotation":0,"scale":1,"position":{"pointX":554.00307083129871,"pointY":117.79168701171898},"width":1095,"sublayerTransform":[1,0,0,0,0,1,0,0,0,0,1,0,0,0,0,1],"contentsRect":{"y":0,"x":0,"width":1,"height":1},"opacity":1,"edgeAntialiasingMask":0,"height":42,"hidden":false,"anchorPoint":{"pointX":0.5,"pointY":0.5}},"texture":"C51349F0E43DB4FB3CF1ABCE18B00245"},{"animations":[],"layers":[],"texturedRectangle":{"singleTextureOpacity":1,"textXHeight":0.6037946428571429,"textBaseline":0.9155053070613316,"isBackgroundTexture":false,"isVerticalText":false,"textColor":[0.21997910737991333,0.21857796609401703,0.22138024866580963,1],"textureType":6},"initialState":{"affineTransform":[1,0,0,1,0,0],"masksToBounds":false,"rotation":0,"scale":1,"position":{"pointX":230.50307083129869,"pointY":201.29168701171898},"width":448,"sublayerTransform":[1,0,0,0,0,1,0,0,0,0,1,0,0,0,0,1],"contentsRect":{"y":0,"x":0,"width":1,"height":1},"opacity":1,"edgeAntialiasingMask":0,"height":35,"hidden":false,"anchorPoint":{"pointX":0.5,"pointY":0.5}},"texture":"F119794F38BEBA339B2ADE97DA30ED22"},{"animations":[],"layers":[],"texturedRectangle":{"singleTextureOpacity":1,"textXHeight":0.49146075581395349,"textBaseline":0.75215545643207637,"isBackgroundTexture":false,"isVerticalText":false,"textColor":[0.21997910737991333,0.21857796609401703,0.22138024866580963,1],"textureType":6},"initialState":{"affineTransform":[1,0,0,1,0,0],"masksToBounds":false,"rotation":0,"scale":1,"position":{"pointX":666.00307083129871,"pointY":292.29168701171898},"width":1319,"sublayerTransform":[1,0,0,0,0,1,0,0,0,0,1,0,0,0,0,1],"contentsRect":{"y":0,"x":0,"width":1,"height":1},"opacity":1,"edgeAntialiasingMask":0,"height":43,"hidden":false,"anchorPoint":{"pointX":0.5,"pointY":0.5}},"texture":"08CFE66A480ED77D2CFE6207C3B1E0F5"}]}]},{"animations":[],"initialState":{"affineTransform":[1,0,0,1,0,0],"masksToBounds":false,"rotation":0,"scale":1,"position":{"pointX":960,"pointY":540},"width":1920,"sublayerTransform":[1,0,0,0,0,1,0,0,0,0,1,0,0,0,0,1],"contentsRect":{"y":0,"x":0,"width":1,"height":1},"opacity":1,"edgeAntialiasingMask":251658240,"height":1080,"hidden":false,"anchorPoint":{"pointX":0.5,"pointY":0.5}},"layers":[{"animations":[],"initialState":{"affineTransform":[1,0,0,1,0,0],"masksToBounds":false,"rotation":0,"scale":1,"position":{"pointX":826.45411682128906,"pointY":240.18760621547699},"width":1454,"sublayerTransform":[1,0,0,0,0,1,0,0,0,0,1,0,0,0,0,1],"contentsRect":{"y":0,"x":0,"width":1,"height":1},"opacity":1,"edgeAntialiasingMask":251658240,"height":43,"hidden":false,"anchorPoint":{"pointX":0.5,"pointY":0.5}},"layers":[{"animations":[],"layers":[],"texturedRectangle":{"singleTextureOpacity":1,"textXHeight":0.49146075581395349,"textBaseline":0.76562747012737187,"isBackgroundTexture":true,"isVerticalText":false,"textColor":[0.21997910737991333,0.21857796609401703,0.22138024866580963,1],"textureType":6},"initialState":{"affineTransform":[1,0,0,1,0,0],"masksToBounds":false,"rotation":0,"scale":1,"position":{"pointX":732.54588317871094,"pointY":29.81239378452301},"width":1454,"sublayerTransform":[1,0,0,0,0,1,0,0,0,0,1,0,0,0,0,1],"contentsRect":{"y":0,"x":0,"width":1,"height":1},"opacity":1,"edgeAntialiasingMask":0,"height":43,"hidden":false,"anchorPoint":{"pointX":0.5,"pointY":0.5}},"texture":"5DE7B0CC278EBD77E051848EF72AD393"}]}]},{"animations":[],"initialState":{"affineTransform":[1,0,0,1,0,0],"masksToBounds":false,"rotation":0,"scale":1,"position":{"pointX":960,"pointY":540},"width":1920,"sublayerTransform":[1,0,0,0,0,1,0,0,0,0,1,0,0,0,0,1],"contentsRect":{"y":0,"x":0,"width":1,"height":1},"opacity":1,"edgeAntialiasingMask":251658240,"height":1080,"hidden":false,"anchorPoint":{"pointX":0.5,"pointY":0.5}},"layers":[{"animations":[],"initialState":{"affineTransform":[1,0,0,1,0,0],"masksToBounds":false,"rotation":0,"scale":1,"position":{"pointX":742.04576110839832,"pointY":793.44873046874977},"width":1299,"sublayerTransform":[1,0,0,0,0,1,0,0,0,0,1,0,0,0,0,1],"contentsRect":{"y":0,"x":0,"width":1,"height":1},"opacity":1,"edgeAntialiasingMask":251658240,"height":296,"hidden":false,"anchorPoint":{"pointX":0.5,"pointY":0.5}},"objectID":"0CF4FF1B-C915-4A9D-816F-AAEFF1151945","layers":[{"animations":[],"layers":[],"texturedRectangle":{"singleTextureOpacity":1,"textXHeight":0.048191379856418921,"textBaseline":-0.14375428895692569,"isBackgroundTexture":true,"isVerticalText":false,"textColor":[0.37036359310150146,0.37036353349685669,0.37036359310150146,1],"textureType":6},"initialState":{"affineTransform":[1,0,0,1,0,0],"masksToBounds":false,"rotation":0,"scale":1,"position":{"pointX":650.95423889160168,"pointY":190.55126953125023},"width":1299,"sublayerTransform":[1,0,0,0,0,1,0,0,0,0,1,0,0,0,0,1],"contentsRect":{"y":0,"x":0,"width":1,"height":1},"opacity":1,"edgeAntialiasingMask":0,"height":296,"hidden":true,"anchorPoint":{"pointX":0.5,"pointY":0.5}},"texture":"08B4C58F6D9A95559DC4A3C6C6CDFBCB"}]}]},{"animations":[],"initialState":{"affineTransform":[1,0,0,1,0,0],"masksToBounds":false,"rotation":0,"scale":1,"position":{"pointX":960,"pointY":540},"width":1920,"sublayerTransform":[1,0,0,0,0,1,0,0,0,0,1,0,0,0,0,1],"contentsRect":{"y":0,"x":0,"width":1,"height":1},"opacity":1,"edgeAntialiasingMask":251658240,"height":1080,"hidden":false,"anchorPoint":{"pointX":0.5,"pointY":0.5}},"layers":[{"animations":[],"initialState":{"affineTransform":[1,0,0,1,0,0],"masksToBounds":false,"rotation":0,"scale":1,"position":{"pointX":1748.673583984375,"pointY":1058.1215823888779},"width":273,"sublayerTransform":[1,0,0,0,0,1,0,0,0,0,1,0,0,0,0,1],"contentsRect":{"y":0,"x":0,"width":1,"height":1},"opacity":1,"edgeAntialiasingMask":251658240,"height":23,"hidden":false,"anchorPoint":{"pointX":0.5,"pointY":0.5}},"layers":[{"animations":[],"layers":[],"texturedRectangle":{"singleTextureOpacity":1,"textXHeight":0.45940896739130432,"textBaseline":0.72777260386425513,"isBackgroundTexture":true,"isVerticalText":false,"textColor":[0.83603078126907349,0.83603072166442871,0.83603072166442871,1],"textureType":6},"initialState":{"affineTransform":[1,0,0,1,0,0],"masksToBounds":false,"rotation":0,"scale":1,"position":{"pointX":166.326416015625,"pointY":17.878417611122131},"width":273,"sublayerTransform":[1,0,0,0,0,1,0,0,0,0,1,0,0,0,0,1],"contentsRect":{"y":0,"x":0,"width":1,"height":1},"opacity":1,"edgeAntialiasingMask":0,"height":23,"hidden":false,"anchorPoint":{"pointX":0.5,"pointY":0.5}},"texture":"C1D05F54FBF927BDB7F1A842AC0F0C26"}]}]}]}},{"effects":[{"beginTime":0,"baseLayer":{"animations":[],"initialState":{"affineTransform":[1,0,0,1,0,0],"masksToBounds":false,"rotation":0,"scale":1,"position":{"pointX":960,"pointY":540},"width":1920,"sublayerTransform":[1,0,0,0,0,1,0,0,0,0,1,0,0,0,0,1],"contentsRect":{"y":0,"x":0,"width":1,"height":1},"opacity":1,"edgeAntialiasingMask":251658240,"height":1080,"hidden":false,"anchorPoint":{"pointX":0.5,"pointY":0.5}},"objectID":"0","layers":[{"animations":[],"initialState":{"affineTransform":[1,0,0,1,0,0],"masksToBounds":false,"rotation":0,"scale":1,"position":{"pointX":960,"pointY":540},"width":1920,"sublayerTransform":[1,0,0,0,0,1,0,0,0,0,1,-0.00035007912466775983,0,0,0,1],"contentsRect":{"y":0,"x":0,"width":1,"height":1},"opacity":1,"edgeAntialiasingMask":251658240,"height":1080,"hidden":false,"anchorPoint":{"pointX":0.5,"pointY":0.5}},"layers":[{"animations":[],"layers":[],"texturedRectangle":{"isBackgroundTexture":false,"singleTextureOpacity":1,"textureType":0,"textBaseline":0,"textXHeight":0,"isVerticalText":false},"initialState":{"affineTransform":[1,0,0,1,0,0],"masksToBounds":false,"rotation":0,"scale":1,"position":{"pointX":960,"pointY":540},"width":1920,"sublayerTransform":[1,0,0,0,0,1,0,0,0,0,1,0,0,0,0,1],"contentsRect":{"y":0,"x":0,"width":1,"height":1},"opacity":1,"edgeAntialiasingMask":0,"height":1080,"hidden":false,"anchorPoint":{"pointX":0.5,"pointY":0.5}},"texture":"21580B63D286D4108E5375F46570ABFA"},{"animations":[{"additive":false,"timeOffset":0,"beginTime":0,"from":{"scalar":false},"repeatCount":0,"fillMode":"both","duration":0.01,"autoreverses":false,"property":"hidden","to":{"scalar":true},"removedOnCompletion":false}],"layers":[],"texturedRectangle":{"isBackgroundTexture":false,"singleTextureOpacity":1,"textureType":0,"textBaseline":0,"textXHeight":0,"isVerticalText":false},"initialState":{"affineTransform":[1,0,0,1,0,0],"masksToBounds":false,"rotation":0,"scale":1,"position":{"pointX":960,"pointY":540},"width":1920,"sublayerTransform":[1,0,0,0,0,1,0,0,0,0,1,0,0,0,0,1],"contentsRect":{"y":0,"x":0,"width":1,"height":1},"opacity":1,"edgeAntialiasingMask":0,"height":1080,"hidden":false,"anchorPoint":{"pointX":0.5,"pointY":0.5}},"texture":"0FC7CF7E41C9F9791A396D66F4460126"}]}]},"effects":[],"duration":0.01,"type":"transition","attributes":{"direction":0},"name":"none","objectID":"0"}],"automaticPlay":false,"hyperlinks":[],"accessibility":[{"text":"Results","targetRectangle":{"y":89,"x":99,"width":291.80500026598571,"height":100.53440856933594}},{"text":"Alison M. Ashbury, 2022-05-30","targetRectangle":{"y":1050.6215823888779,"x":1643.8827819824219,"width":269.873046875,"height":24}},{"text":"Female orangutans DJLs were significantly predicted by an interaction between FAI and fire period, with a medium effect size ( = 0.55, 95% CI [0.17, 0.93]; Fig. 2c).  (Ashbury et al. 2021)","targetRectangle":{"y":685.44873046875,"x":96.545761108398438,"width":597.59912109375,"height":137}},{"text":"The probability of co-foraging between related females was significantly lower during the post-fire period than during the pre-fire period (medium effect size,  = 0.69, 95% CI [0.12, 1.25], Fig 5b). (Ashbury et al. 2021)","targetRectangle":{"y":822.44873046875,"x":96.545761108398438,"width":621.48779296875,"height":160}},{"text":"The model also suggested that rates of aggression may decrease with increasing familiarity due to previous encounters, although with a relatively small effect (Cohen's D = 0.278, p = 0.067). (Morisson et al. 2020)","targetRectangle":{"y":753.44873046875,"x":778.25121203157551,"width":619.1015625,"height":160}},{"text":"Plainly describe what your data shows (no methods or interpretation)","targetRectangle":{"y":317.20831298828125,"x":110.21121215820312,"width":1231.46484375,"height":47}},{"text":"Figures and Tables as focal points, text builds around these ","targetRectangle":{"y":359.50831186771393,"x":110.21121215820312,"width":1060.09765625,"height":92}},{"text":"Break into subsections","targetRectangle":{"y":446.80831074714661,"x":110.21121215820312,"width":404.51171875,"height":92}},{"text":"Use appropriate technical language, include necessary statsy numbers","targetRectangle":{"y":534.10830962657928,"x":110.21121215820312,"width":1275.37109375,"height":92}},{"text":"What does my audience need to know in order to trust the conclusions of my study?","targetRectangle":{"y":222.68760621547699,"x":103.45411682128906,"width":1452.8125,"height":47}}],"baseLayer":{"animations":[],"initialState":{"affineTransform":[1,0,0,1,0,0],"masksToBounds":false,"rotation":0,"scale":1,"position":{"pointX":960,"pointY":540},"width":1920,"sublayerTransform":[1,0,0,0,0,1,0,0,0,0,1,0,0,0,0,1],"contentsRect":{"y":0,"x":0,"width":1,"height":1},"opacity":1,"edgeAntialiasingMask":251658240,"height":1080,"hidden":false,"anchorPoint":{"pointX":0.5,"pointY":0.5}},"objectID":"0","layers":[{"animations":[],"initialState":{"affineTransform":[1,0,0,1,0,0],"masksToBounds":false,"rotation":0,"scale":1,"position":{"pointX":960,"pointY":540},"width":1920,"sublayerTransform":[1,0,0,0,0,1,0,0,0,0,1,-0.00035007912466775983,0,0,0,1],"contentsRect":{"y":0,"x":0,"width":1,"height":1},"opacity":1,"edgeAntialiasingMask":251658240,"height":1080,"hidden":false,"anchorPoint":{"pointX":0.5,"pointY":0.5}},"layers":[{"animations":[],"layers":[],"texturedRectangle":{"isBackgroundTexture":false,"singleTextureOpacity":1,"textureType":0,"textBaseline":0,"textXHeight":0,"isVerticalText":false},"initialState":{"affineTransform":[1,0,0,1,0,0],"masksToBounds":false,"rotation":0,"scale":1,"position":{"pointX":960,"pointY":540},"width":1920,"sublayerTransform":[1,0,0,0,0,1,0,0,0,0,1,0,0,0,0,1],"contentsRect":{"y":0,"x":0,"width":1,"height":1},"opacity":1,"edgeAntialiasingMask":0,"height":1080,"hidden":false,"anchorPoint":{"pointX":0.5,"pointY":0.5}},"texture":"0FC7CF7E41C9F9791A396D66F4460126"}]}]}}]}